Workbook

Sheet Dirty_Retail_Data
A1: Order ID | B1: Order Date | C1: Ship Date | D1: Customer Name | E1: Segment | F1: Region | G1: State | H1: City | I1: Category | J1: Sub-Category | K1: Product Name | L1: Quantity | M1: Unit Price | N1: Discount | O1: Sales | P1: Profit | Q1: Ship Mode | R1: Payment Type
A2: ORD-1001 | B2: 2023-04-25 | C2: 2023-05-04 | D2: Meera Patel | E2: Home Office | F2: South | G2: California | H2: San Francisco | I2: Technology | J2: Accessories | K2: Keyboard | L2: 5 | M2: 116.24 | N2: 0.05 | O2: 552.14 | P2: 87.67 | Q2: Standard Class | R2: Card
A3: ORD-1002 | B3: 2023-08-27 | C3: 2023-09-05 | D3: Anaya Rao | E3: Consumer | F3: South | G3: Illinois | H3: Peoria | I3: Furniture | J3: Tables | K3: Side Table | L3: 1 | M3: 256.07 | N3: 0.3 | O3: 179.25 | P3: 21.32 | Q3: First Class | R3: Card
A4: ORD-1003 | B4: 2024-12-15 | C4: 2024-12-22 | D4: Meera Patel | E4: Corporate | F4: Central | G4: Florida | H4: Orlando | I4: Furniture | J4: Tables | K4: Side Table | L4: 5 | M4: 76.72 | N4: 0.1 | O4: 345.24 | P4: -45.91 | Q4: First Class | R4: Card
A5: ORD-1004 | B5: 2024-04-15 | C5: 2024-04-21 | D5: Sara Khan | E5: Home Office | F5: West | G5: Illinois | H5: Chicago | I5: Technology | J5: Accessories | K5: Keyboard | L5: 7 | M5: 42.83 | N5: 0.1 | O5: 269.83 | P5: 54.38 | Q5: Second Class | R5: Bank Transfer
A6: ORD-1005 | B6: 2023-08-27 | C6: 2023-09-02 | D6: Sara Khan | E6: Home Office | F6: Central | G6: California | H6: San Diego | I6: Furniture | J6: Chairs | K6: Visitor Chair | L6: 5 | M6: 208.41 | N6: 0.1 | O6: 937.85 | P6: -98.64 | Q6: Standard Class | R6: Cash
A7: ORD-1006 | B7: 2023-09-08 | C7: 2023-09-12 | D7: Dev Mehta | E7: Consumer | F7: East | G7: New York | H7: Buffalo | I7: Technology | J7: Phones | K7: Desk Phone | L7: 7 | M7: 127.32 | N7: 0.3 | O7: 623.87 | P7: 85.19 | Q7: First Class | R7: Digital Wallet
A8: ORD-1007 | B8: 2023-03-09 | C8: 2023-03-17 | D8: Kabir Joshi | E8: Corporate | F8: East | G8: New York | H8: Albany | I8: Office Supplies | J8: Binders | K8: Ring Binder | L8: 6 | M8: 101.98 | N8: 0.15 | O8: 520.1 | P8: 1.04 | Q8: First Class | R8: Digital Wallet
A9: ORD-1008 | B9: 2024-02-13 | C9: 2024-02-15 | E9: Home Office | F9: East | G9: Texas | H9: Houston | I9: Technology | J9: Phones | K9: Wireless Phone | L9: 3 | M9: 233.21 | N9: 0 | O9: 699.63 | P9: 117.3 | Q9: Same Day | R9: Card
A10: ORD-1009 | B10: 2024-01-26 | C10: 2024-01-28 | D10: Riya Desai | E10: Home Office | F10: Central | G10: Illinois | H10: Springfield | I10: Office Supplies | J10: Paper | K10: A4 Paper | L10: 5 | M10: 437.22 | N10: 0 | O10: 2186.1 | P10: 290.6 | Q10: First Class | R10: Digital Wallet
A11: ORD-1010 | B11: 2024-04-09 | C11: 2024-04-11 | D11: Riya Desai | E11: Home Office | F11: East | G11: California | H11: San Francisco | I11: Furniture | J11: Tables | K11: Office Table | L11: 5 | M11: 437.57 | N11: 0.05 | O11: 2078.46 | P11: 111.27 | Q11: First Class | R11: Cash
A12: ORD-1011 | B12: 2024-06-27 | C12: 2024-07-02 | D12: Sara Khan | E12: Consumer | F12: East | G12: California | H12: San Francisco | I12: Technology | J12: Phones | K12: Wireless Phone | L12: 6 | M12: 223.96 | N12: 0 | O12: 1343.76 | P12: 332.43 | Q12: Standard Class | R12: Card
A13: ORD-1012 | B13: 2024-05-12 | C13: 2024-05-15 | D13: Riya Desai | E13: Home Office | F13: South | G13: California | H13: San Francisco | I13: Technology | J13: Accessories | K13: Keyboard | L13: 3 | M13: 64.75 | N13: 0.15 | O13: 165.11 | P13: 42.19 | Q13: Second Class | R13: Bank Transfer
A14: ORD-1013 | B14: 2024-11-18 | C14: 2024-11-22 | D14: Meera Patel | E14: Corporate | F14: West | G14: Washington | H14: Spokane | I14: Office Supplies | J14: Paper | K14: Copy Paper | L14: 8 | M14: 405.63 | N14: 0.15 | O14: 2758.28 | P14: -342.96 | Q14: Second Class | R14: Cash
A15: ORD-1014 | B15: 2023-03-14 | C15: 2023-03-16 | D15: Sara Khan | E15: Corporate | F15: west | G15: Washington | H15: Tacoma | I15: Furniture | J15: Chairs | K15: Ergo Chair | L15: 1 | M15: 109.19 | N15: 0 | O15: 109.19 | P15: 23.52 | Q15: Second Class | R15: Digital Wallet
A16: ORD-1015 | B16: 2024-04-29 | C16: 2024-05-06 | D16: Ishaan Verma | E16: Home Office | F16: West | G16: Florida | H16: Miami | I16: Furniture | J16: Tables | K16: Side Table | L16: 2 | M16: 50.84 | N16: 0.15 | O16: 86.43 | P16: -1.47 | Q16: Standard Class | R16: Card
A17: ORD-1016 | B17: 2023-12-14 | C17: 2023-12-17 | D17: Riya Desai | E17: Corporate | F17: East | G17: California | H17: Los Angeles | I17: Office Supplies | J17: Paper | K17: A4 Paper | L17: 4 | M17: 92.07 | N17: 0.15 | O17: 313.04 | P17: -36.16 | Q17: Same Day | R17: Card
A18: ORD-1017 | B18: 2024-10-29 | C18: 2024-11-06 | D18: Ishaan Verma | E18: Consumer | F18: South | G18: Illinois | H18: Chicago | I18: Furniture | J18: Chairs | K18: Ergo Chair | L18: 2 | M18: 417.45 | N18: 0.05 | O18: 793.15 | P18: -82.09 | Q18: Second Class | R18: Digital Wallet
A19: ORD-1018 | B19: 2024-02-04 | C19: 2024-02-13 | D19: Ishaan Verma | E19: Consumer | F19: East | G19: Texas | H19: Dallas | I19: Furniture | J19: Chairs | K19: Office Chair | L19: 5 | M19: 194.97 | N19: 0.3 | O19: 682.39 | P19: 189.63 | Q19: Second Class | R19: Card
A20: ORD-1019 | B20: 2024-07-09 | C20: 2024-07-18 | D20: Kabir Joshi | E20: Consumer | F20: West | G20: California | H20: San Francisco | I20: Technology | J20: Phones | K20: Desk Phone | L20: N/A | M20: 33.27 | N20: 0.2 | O20: 159.7 | P20: 6.28 | Q20: Standard Class | R20: Card
A21: ORD-1020 | B21: 2023-08-29 | C21: 2023-09-05 | D21: Dev Mehta | E21: Corporate | F21: East | G21: Florida | H21: Miami | I21: Technology | J21: Accessories | K21: Webcam | L21: 4 | M21: 263.88 | N21: 0 | O21: 1055.52 | P21: 110.74 | Q21: First Class | R21: Cash
A22: ORD-1021 | B22: 2024-02-10 | C22: 2024-02-12 | D22: Meera Patel | E22: Home Office | F22: East | G22: New York | H22: Albany | I22: Office Supplies | J22: Binders | K22: File Binder | L22: 5 | M22: 210.09 | N22: 0 | O22: 1050.45 | P22: -184.58 | Q22: First Class | R22: Cash
A23: ORD-1022 | B23: 2023-03-12 | C23: 2023-03-21 | D23: Aarav Shah | E23: Home Office | F23: Central | G23: New York | H23: Buffalo | I23: Office Supplies | J23: Binders | K23: File Binder | L23: 5 | M23: 77.72 | N23: 0.2 | O23: 310.88 | P23: 44.65 | Q23: Standard Class | R23: Cash
A24: ORD-1023 | B24: 2023-04-29 | C24: 2023-05-05 | D24: Sara Khan | E24: Home Office | G24: California | H24: San Francisco | I24: Office Supplies | J24: Binders | K24: File Binder | L24: 3 | M24: 128.38 | N24: 0.2 | O24: 308.11 | P24: -25.61 | Q24: Same Day | R24: Bank Transfer
A25: ORD-1024 | B25: 2023-04-05 | C25: 2023-04-10 | D25: Kabir Joshi | E25: Home Office | F25: South | G25: Washington | H25: Spokane | I25: Furniture | J25: Chairs | K25: Visitor Chair | L25: 5 | M25: 27.49 | N25: 0.1 | O25: 123.7 | P25: 21.61 | Q25: Same Day | R25: Card
A26: ORD-1025 | B26: 2023-03-19 | C26: 2023-03-26 | D26: Kabir Joshi | E26: Consumer | F26: Central | G26: Washington | H26: Seattle | I26: Furniture | J26: Chairs | K26: Office Chair | L26: 1 | M26: 376.89 | N26: 0.2 | O26: 301.51 | P26: 22.36 | Q26: Standard Class | R26: Bank Transfer
A27: ORD-1026 | B27: 2024-11-29 | C27: 2024-12-06 | D27: Kabir Joshi | E27: Consumer | F27: East | G27: New York | H27: Albany | I27: Furniture | J27: Tables | K27: Office Table | L27: 2 | M27: 164.33 | N27: 0.2 | O27: 262.93 | P27: 59.61 | Q27: Same Day | R27: Card
A28: ORD-1027 | B28: 2023-12-07 | C28: 2023-12-08 | D28: Ishaan Verma | E28: Consumer | F28: East | G28: Florida | H28: Tampa | I28: Furniture | J28: Tables | K28: Conference Table | L28: 4 | M28: 125.93 | N28: 0.3 | O28: 352.6 | P28: -45.94 | Q28: First Class | R28: Bank Transfer
A29: ORD-1028 | B29: 2023-08-17 | C29: 2023-08-22 | D29: Dev Mehta | E29: Home Office | F29: South | G29: California | H29: San Francisco | I29: Furniture | J29: Tables | K29: Side Table | L29: 4 | M29: 184.12 | N29: 0.1 | O29: 662.83 | P29: 144.23 | Q29: First Class | R29: Card
A30: ORD-1029 | B30: 2023-09-25 | C30: 2023-10-01 | D30: Anaya Rao | E30: Home Office | F30: West | G30: New York | H30: Albany | I30: Furniture | J30: Chairs | K30: Office Chair | L30: 5 | M30: 24.91 | N30: 0.2 | O30: 99.64 | P30: 1.98 | Q30: Second Class | R30: Bank Transfer
A31: ORD-1030 | B31: 2024-12-26 | C31: 2025-01-01 | D31: Dev Mehta | E31: Home Office | F31: West | G31: Florida | H31: Miami | I31: Furniture | J31: Chairs | K31: Visitor Chair | L31: 4 | M31: unknown | N31: 0 | O31: 675.96 | P31: 173.37 | Q31: First Class | R31: Bank Transfer
A32: ORD-1031 | B32: 2024-02-23 | C32: 2024-03-01 | D32: Kabir Joshi | E32: Home Office | F32: Central | G32: Texas | H32: Dallas | I32: Technology | J32: Accessories | K32: Mouse | L32: 5 | M32: 253.05 | N32: 0.05 | O32: 1201.99 | P32: 16.11 | Q32: Standard Class | R32: Bank Transfer
A33: ORD-1032 | B33: 2023-08-04 | C33: 2023-08-13 | D33: Ishaan Verma | E33: Home Office | F33: East | G33: Florida | H33: Tampa | I33: Office Supplies | J33: Binders | K33: File Binder | L33: 6 | M33: 213.52 | N33: 0.15 | O33: 1088.95 | P33: 142.42 | Q33: Standard Class | R33: Bank Transfer
A34: ORD-1033 | B34: 2024-11-10 | C34: 2024-11-14 | D34: Sara Khan | E34: Consumer | F34: West | G34: Washington | H34: Tacoma | I34: Technology | J34: Phones | K34: Desk Phone | L34: 6 | M34: 49.28 | N34: 0.05 | O34: 280.9 | P34: 36.37 | Q34: Second Class | R34: Digital Wallet
A35: ORD-1034 | B35: 2023-03-16 | C35: 2023-03-20 | D35: Kabir Joshi | E35: Home Office | F35: West | G35: Florida | H35: Orlando | I35: Technology | J35: Phones | K35: Desk Phone | L35: 4 | M35: 325.51 | N35: 0.15 | O35: 1106.73 | P35: 52.47 | Q35: Same Day | R35: Cash
A36: ORD-1035 | B36: 2024-12-13 | C36: 2024-12-21 | D36: Dev Mehta | E36: Corporate | F36: South | G36: Illinois | H36: Springfield | I36: Furniture | J36: Tables | K36: Side Table | L36: 1 | M36: 254.37 | N36: 0 | O36: 254.37 | P36: 7.62 | Q36: Same Day | R36: Cash
A37: ORD-1036 | B37: 2024-05-01 | C37: 2024-05-10 | D37: Ishaan Verma | E37: Home Office | F37: East | G37: Florida | H37: Orlando | I37: Technology | J37: Accessories | K37: Mouse | L37: 4 | M37: 379.22 | N37: 0.1 | O37: 1365.19 | P37: 235.19 | Q37: Same Day | R37: Card
A38: ORD-1037 | B38: 2023-10-20 | C38: 2023-10-23 | D38: Sara Khan | E38: Corporate | F38: East | G38: New York | H38: Buffalo | I38: technology | J38: Accessories | K38: Webcam | L38: 6 | M38: 149.31 | N38: 0.2 | O38: 716.69 | P38: -102.44 | Q38: Second Class | R38: Card
A39: ORD-1038 | B39: 2024-02-22 | C39: 2024-02-29 | D39: Aarav Shah | E39: Home Office | F39: South | G39: Texas | H39: Austin | I39: Office Supplies | J39: Paper | K39: Notebook Paper | L39: 8 | M39: 191.77 | N39: 0.05 | O39: 1457.45 | P39: 296.05 | Q39: Standard Class | R39: Bank Transfer
A40: ORD-1039 | B40: 2024-02-04 | C40: 2024-02-05 | D40: Anaya Rao | E40: Corporate | F40: South | G40: Florida | H40: Tampa | I40: Office Supplies | J40: Binders | K40: File Binder | L40: 4 | M40: 223.8 | N40: 0.1 | O40: 805.68 | P40: 16.5 | Q40: Second Class | R40: Digital Wallet
A41: ORD-1040 | B41: 2024-09-29 | C41: 2024-10-06 | D41: Kabir Joshi | E41: Corporate | F41: East | G41: Illinois | H41: Chicago | I41: Furniture | J41: Tables | K41: Office Table | L41: 7 | M41: 269.62 | N41: 0.3 | O41: 1321.14 | P41: -221.33 | Q41: First Class | R41: Digital Wallet
A42: ORD-1041 | B42: 2023-08-05 | C42: 2023-08-12 | D42: Riya Desai | E42: Consumer | F42: South | G42: Florida | H42: Orlando | I42: Office Supplies | J42: Binders | K42: Ring Binder | L42: 6 | M42: 344.46 | N42: 0.15 | O42: 1756.75 | P42: -91.35 | Q42: Standard Class | R42: Bank Transfer
A43: ORD-1042 | B43: 2024-10-27 | D43: Kabir Joshi | E43: Consumer | F43: East | G43: California | H43: San Francisco | I43: Furniture | J43: Tables | K43: Conference Table | L43: 1 | M43: 341.37 | N43: 0.05 | O43: 324.3 | P43: -28.63 | Q43: Standard Class | R43: Cash
A44: ORD-1043 | B44: 2024-12-17 | C44: 2024-12-20 | D44: Riya Desai | E44: Consumer | F44: West | G44: Texas | H44: Dallas | I44: Office Supplies | J44: Paper | K44: Notebook Paper | L44: 3 | M44: 275.8 | N44: 0.3 | O44: 579.18 | P44: 87.13 | Q44: Same Day | R44: Digital Wallet
A45: ORD-1044 | B45: 2023-07-23 | C45: 2023-07-25 | D45: Aarav Shah | E45: Corporate | F45: South | G45: California | H45: San Francisco | I45: Technology | J45: Accessories | K45: Webcam | L45: 4 | M45: 53.04 | N45: 0.1 | O45: 190.94 | P45: 40.31 | Q45: First Class | R45: Card
A46: ORD-1045 | B46: 2024-10-25 | C46: 2024-10-31 | D46: Ishaan Verma | E46: Home Office | F46: East | G46: Texas | H46: Houston | I46: Technology | J46: Phones | K46: Smartphone | L46: 7 | M46: 371.47 | N46: 0 | O46: 2600.29 | P46: 50.5 | Q46: Second Class | R46: Bank Transfer
A47: ORD-1046 | B47: 2024-07-05 | C47: 2024-07-09 | D47: Meera Patel | E47: Corporate | F47: South | G47: Florida | H47: Orlando | I47: Technology | J47: Phones | K47: Desk Phone | L47: 7 | M47: 372.97 | N47: 0.2 | O47: 2088.63 | P47: -118.09 | Q47: Same Day | R47: Digital Wallet
A48: ORD-1047 | B48: 2023-01-30 | C48: 2023-02-05 | D48: Riya Desai | E48: Home Office | F48: Central | G48: Florida | H48: Orlando | I48: Office Supplies | J48: Binders | K48: File Binder | L48: 3 | M48: 223.5 | N48: 0.1 | O48: 603.45 | P48: 112.85 | Q48: Standard Class | R48: Cash
A49: ORD-1048 | B49: 2023-09-05 | C49: 2023-09-13 | D49: Ishaan Verma | E49: Consumer | F49: West | G49: Washington | H49: Spokane | I49: Furniture | J49: Chairs | K49: Office Chair | L49: 8 | M49: 253.39 | N49: 0.05 | O49: 1925.76 | P49: 265.14 | Q49: Second Class | R49: Digital Wallet
A50: ORD-1049 | B50: 2023-09-07 | C50: 2023-09-16 | D50: Dev Mehta | E50: Corporate | F50: South | G50: Texas | H50: Austin | I50: Technology | J50: Accessories | K50: Mouse | L50: 6 | M50: 217.18 | N50: 0.2 | O50: 1042.46 | P50: -22.8 | Q50: First Class | R50: Bank Transfer
A51: ORD-1050 | B51: 2023-05-04 | C51: 2023-05-07 | D51: Sara Khan | E51: Consumer | F51: South | G51: Washington | H51: Seattle | I51: Furniture | J51: Tables | K51: Conference Table | L51: 6 | M51: 60.84 | N51: 0.2 | O51: 292.03 | P51: 75.17 | Q51: First Class | R51: Card
A52: ORD-1051 | B52: 2023-10-31 | C52: 2023-11-05 | D52: Aarav Shah | E52: Consumer | F52: Central | G52: New York | H52: Buffalo | I52: Furniture | J52: Tables | K52: Side Table | L52: 3 | M52: 141.6 | N52: 0.3 | O52: 297.36 | P52: 19.54 | Q52: Second Class | R52: Digital Wallet
A53: ORD-1052 | B53: 2023-01-13 | C53: 2023-01-14 | D53: Riya Desai | E53: Corporate | F53: West | G53: Illinois | H53: Springfield | I53: Furniture | J53: Chairs | K53: Ergo Chair | L53: 8 | M53: 219.59 | N53: 0.1 | O53: 1581.05 | P53: -150.5 | Q53: Same Day | R53: Digital Wallet
A54: ORD-1053 | B54: 2024-08-13 | C54: 2024-08-15 | D54: Sara Khan | E54: Consumer | F54: South | G54: Washington | H54: Tacoma | I54: Furniture | J54: Chairs | K54: Visitor Chair | L54: 1 | M54: 75.06 | N54: 0.2 | O54: 60.05 | P54: 15.41 | Q54: Second Class | R54: Digital Wallet
A55: ORD-1054 | B55: 2024-03-29 | C55: 2024-03-31 | D55: Sara Khan | E55: Home Office | F55: East | G55: Texas | H55: Austin | I55: Office Supplies | J55: Paper | K55: Notebook Paper | L55: 7 | M55: 142.98 | N55: 0.2 | O55: 800.69 | P55: -121.94 | Q55: Standard Class | R55: Cash
... A65: ORD-1064 | B65: 2023-07-15 | C65: 2023-07-22 | D65: Dev Mehta | E65: Home Office | F65: Central | G65: Illinois | H65: Peoria | I65: Office Supplies | J65: Paper | K65: A4 Paper | L65: 3 | M65: 389.9 | N65: 0.1 | O65: 1052.73 | P65: 184.68 | Q65: First Class | R65: Bank Transfer
A66: ORD-1065 | B66: 2024-08-16 | C66: 2024-08-25 | D66: Anaya Rao | E66: Corporate | F66: Central | G66: Washington | H66: Spokane | I66: Technology | J66: Phones | K66: Desk Phone | L66: 3 | M66: 205.37 | N66: 0.15 | P66: -11.12 | Q66: Second Class | R66: Digital Wallet
A67: ORD-1066 | B67: 2024-02-25 | C67: 2024-02-28 | D67: Ishaan Verma | E67: Consumer | F67: East | G67: California | H67: San Diego | I67: Furniture | J67: Tables | K67: Side Table | L67: 8 | M67: 319.71 | N67: 0.15 | O67: 2174.03 | P67: -5.23 | Q67: First Class | R67: Card
A68: ORD-1067 | B68: 2023-04-13 | C68: 2023-04-16 | D68: Meera Patel | E68: Corporate | F68: Central | G68: Illinois | H68: Springfield | I68: Office Supplies | J68: Paper | K68: Notebook Paper | L68: 1 | M68: 327.32 | N68: 0.15 | O68: 278.22 | P68: 61.38 | Q68: Same Day | R68: Card
A69: ORD-1068 | B69: 2024-11-21 | C69: 2024-11-22 | D69: Meera Patel | E69: Consumer | F69: Central | G69: Illinois | H69: Springfield | I69: Office Supplies | J69: Binders | K69: Ring Binder | L69: 6 | M69: 285.05 | N69: 0.15 | O69: 1453.76 | P69: 321.71 | Q69: Standard Class | R69: Digital Wallet
A70: ORD-1069 | B70: 2024-10-10 | C70: 2024-10-11 | D70: Dev Mehta | E70: Consumer | F70: Central | G70: Washington | H70: Seattle | I70: Furniture | J70: Chairs | K70: Office Chair | L70: 8 | M70: 81.53 | N70: 0.1 | O70: 587.02 | P70: 138.29 | Q70: First Class | R70: Digital Wallet
A71: ORD-1070 | B71: 2023-09-08 | C71: 2023-09-15 | D71: Sara Khan | E71: Corporate | F71: East | G71: Illinois | H71: Springfield | I71: Furniture | J71: Tables | K71: Office Table | L71: 3 | M71: 83.13 | N71: 0 | O71: 249.39 | P71: 25.03 | Q71: Same Day | R71: Bank Transfer
A72: ORD-1071 | B72: 2023-09-19 | C72: 2023-09-21 | D72: Ishaan Verma | E72: Corporate | F72: Central | G72: Washington | H72: Seattle | I72: Office Supplies | J72: Paper | K72: Copy Paper | L72: 8 | M72: 406.33 | N72: 0.3 | O72: 2275.45 | P72: 162.55 | Q72: Same Day | R72: Bank Transfer
A73: ORD-1072 | B73: 2023-11-06 | C73: 2023-11-11 | D73: Riya Desai | E73: Consumer | F73: South | G73: New York | H73: Buffalo | I73: Office Supplies | J73: Paper | K73: Notebook Paper | L73: 8 | M73: 55.14 | N73: 0.15 | O73: 374.95 | P73: 31.15 | Q73: Standard Class | R73: Card
A74: ORD-1073 | B74: 2024-05-23 | C74: 2024-05-26 | D74: Meera Patel | E74: Home Office | F74: West | G74: Texas | H74: Houston | I74: Technology | J74: Phones | K74: Smartphone | L74: 6 | M74: 104.8 | N74: 0.05 | O74: 597.36 | P74: 63.09 | Q74: Same Day | R74: Card
A75: ORD-1074 | B75: 2024-01-09 | C75: 2024-01-12 | D75: Sara Khan | E75: Consumer | F75: Central | G75: Washington | H75: Seattle | I75: Technology | J75: Phones | K75: Wireless Phone | L75: 2 | M75: 410.06 | N75: 0.1 | O75: 738.11 | P75: 120.93 | Q75: First Class | R75: Cash
A76: ORD-1075 | B76: 2024-05-08 | C76: 2024-05-11 | D76: Sara Khan | E76: Home Office | F76: South | G76: Texas | H76: Austin | I76: Office Supplies | J76: Binders | K76: File Binder | L76: 6 | M76: 363.47 | N76: 0.15 | O76: 1853.7 | P76: 487.4 | Q76: First Class | R76: Card
A77: ORD-1076 | B77: 2023-01-15 | C77: 2023-01-20 | D77: Anaya Rao | E77: Home Office | F77: Central | G77: Texas | H77: Austin | I77: Office Supplies | J77: Paper | K77: A4 Paper | L77: 2 | M77: 209.02 | N77: 10% | O77: 292.63 | P77: 48.15 | Q77: Second Class | R77: Digital Wallet
A78: ORD-1077 | B78: 2024-09-26 | C78: 2024-10-01 | D78: Anaya Rao | E78: Consumer | F78: East | G78: Illinois | H78: Springfield | I78: Furniture | J78: Chairs | K78: Ergo Chair | L78: 4 | M78: 294.26 | N78: 0.3 | O78: 823.93 | P78: 163.94 | Q78: Standard Class | R78: Bank Transfer
A79: ORD-1078 | B79: 2023-04-29 | C79: 2023-05-08 | D79: Anaya Rao | E79: Home Office | F79: East | G79: California | H79: Los Angeles | I79: Office Supplies | J79: Paper | K79: Notebook Paper | L79: 3 | M79: 179.78 | N79: 0.1 | O79: 485.41 | P79: 62.34 | Q79: Standard Class | R79: Digital Wallet
A80: ORD-1079 | B80: 2024-02-22 | C80: 2024-02-28 | D80: Meera Patel | E80: Home Office | F80: Central | G80: Texas | H80: Houston | I80: Technology | J80: Phones | K80: Wireless Phone | L80: 6 | M80: 104.03 | N80: 0.15 | O80: 530.55 | P80: 136.49 | Q80: First Class | R80: Card
A81: ORD-1080 | B81: 2023-10-10 | C81: 2023-10-11 | D81: Aarav Shah | E81: Corporate | F81: East | G81: New York | H81: New York City | I81: Office Supplies | J81: Paper | K81: A4 Paper | L81: 8 | M81: 48.52 | N81: 0.05 | O81: 368.75 | P81: 42.47 | Q81: Second Class | R81: Card
A82: ORD-1081 | B82: 2023-08-01 | C82: 2023-08-02 | D82: Riya Desai | E82: Consumer | F82: East | G82: Illinois | H82: Chicago | I82: Technology | J82: Phones | K82: Wireless Phone | L82: 4 | M82: 153.22 | N82: 0.05 | O82: 582.24 | P82: 106.42 | Q82: First Class | R82: Cash
A83: ORD-1082 | B83: 2024-11-07 | C83: 2024-11-08 | D83: Kabir Joshi | E83: Corporate | F83: West | G83: California | H83: Los Angeles | I83: Furniture | J83: Chairs | K83: Ergo Chair | L83: 1 | M83: 166.34 | N83: 0.05 | O83: 158.02 | P83: 14.36 | Q83: Same Day | R83: Card
A84: ORD-1083 | B84: 2023-03-07 | C84: 2023-03-11 | D84: Aarav Shah | E84: Home Office | F84: Central | G84: Florida | H84: Orlando | I84: Technology | J84: Accessories | K84: Mouse | L84: 6 | M84: 234.85 | N84: 0 | O84: 1409.1 | P84: 39.35 | Q84: Standard Class | R84: Card
A85: ORD-1084 | B85: 2024-02-16 | C85: 2024-02-18 | D85: Dev Mehta | E85: Home Office | F85: East | G85: Florida | H85: Tampa | I85: Office Supplies | J85: Paper | K85: A4 Paper | L85: 2 | M85: 224.7 | N85: 0.15 | O85: 381.99 | P85: -55.84 | Q85: Second Class | R85: Bank Transfer
A86: ORD-1085 | B86: 2024-10-10 | C86: 2024-10-18 | D86: Anaya Rao | E86: Consumer | F86: West | G86: Illinois | H86: Peoria | I86: Technology | J86: Phones | K86: Wireless Phone | L86: 6 | M86: 176.36 | N86: 0.2 | O86: 846.53 | P86: 54.23 | Q86: Second Class | R86: Digital Wallet
A87: ORD-1086 | B87: 2023-08-22 | C87: 2023-08-29 | D87: Dev Mehta | E87: Home Office | F87: Central | G87: Florida | H87: Orlando | I87: Office Supplies | J87: Paper | K87: Notebook Paper | L87: 8 | M87: 184.24 | N87: 0.3 | O87: 1031.74 | P87: -140.59 | Q87: Second Class | R87: Digital Wallet
A88: ORD-1087 | B88: 2023-04-04 | C88: 2023-04-07 | D88: Aarav Shah | E88: Home Office | F88: Central | G88: California | H88: Los Angeles | I88: Furniture | J88: Chairs | K88: Visitor Chair | L88: 7 | M88: 50.68 | N88: 0.3 | O88: 248.33 | P88: -2.13 | Q88: Standard Class | R88: Digital Wallet
A89: ORD-1088 | B89: 2024-11-12 | C89: 2024-11-14 | D89: Sara Khan | E89: Consumer | F89: South | G89: Florida | H89: Tampa | I89: Office Supplies | J89: Binders | K89: Ring Binder | L89: 1 | M89: 436.03 | N89: 0.2 | O89: 348.82 | P89: -12.65 | Q89: Standard Class | R89: Bank Transfer
A90: ORD-1089 | B90: 2024-01-12 | C90: 2024-01-21 | D90: Aarav Shah | E90: Home Office | F90: Central | G90: California | H90: San Diego | I90: Technology | J90: Phones | L90: 4 | M90: 364.79 | N90: 0.2 | O90: 1167.33 | P90: 313.18 | Q90: Second Class | R90: Bank Transfer
A91: ORD-1090 | B91: 2023-11-13 | C91: 2023-11-20 | D91: Meera Patel | E91: Consumer | F91: West | G91: Texas | H91: Dallas | I91: Technology | J91: Accessories | K91: Keyboard | L91: 1 | M91: 88.18 | N91: 0.05 | O91: 83.77 | P91: 6.74 | Q91: Second Class | R91: Digital Wallet
A92: ORD-1091 | B92: 2024-04-09 | C92: 2024-04-11 | D92: Aarav Shah | E92: Consumer | F92: East | G92: Texas | H92: Houston | I92: Office Supplies | J92: Paper | K92: Copy Paper | L92: 6 | M92: 145.74 | N92: 0.1 | O92: 787 | P92: 139.57 | Q92: Standard Class | R92: Card
A93: ORD-1092 | B93: 2024-03-29 | C93: 2024-04-07 | D93: Meera Patel | E93: Consumer | F93: South | G93: Washington | H93: Spokane | I93: Office Supplies | J93: Binders | K93: Ring Binder | L93: 8 | M93: 276.33 | N93: 0.15 | O93: 1879.04 | P93: -102.11 | Q93: First Class | R93: Digital Wallet
A94: ORD-1093 | B94: 2024-11-14 | C94: 2024-11-18 | D94: Riya Desai | E94: Consumer | F94: East | G94: Texas | H94: Houston | I94: Technology | J94: Phones | K94: Smartphone | L94: 4 | M94: 182.71 | N94: 0.2 | O94: 584.67 | P94: -90.51 | Q94: First Class | R94: Bank Transfer
A95: ORD-1094 | B95: 2023-01-08 | C95: 2023-01-12 | D95: Dev Mehta | E95: Consumer | F95: South | G95: Florida | H95: Tampa | I95: Furniture | J95: Chairs | K95: Visitor Chair | L95: 7 | M95: 85.66 | N95: 0.15 | O95: 509.68 | P95: 33.12 | Q95: Standard Class | R95: Digital Wallet
A96: ORD-1095 | B96: 2024-04-15 | C96: 2024-04-20 | D96: Meera Patel | E96: Corporate | F96: West | G96: California | H96: San Diego | I96: Furniture | J96: Chairs | K96: Office Chair | L96: 7 | M96: 261.44 | N96: 0.3 | O96: 1281.06 | P96: 146.64 | Q96: Second Class | R96: Digital Wallet
A97: ORD-1096 | B97: 2024-01-06 | C97: 2024-01-08 | D97: Anaya Rao | E97: Corporate | F97: Central | G97: California | H97: San Diego | I97: Technology | J97: Accessories | K97: Keyboard | L97: 2 | M97: 115.55 | N97: 0.2 | O97: 184.88 | P97: 0.78 | Q97: First Class | R97: Cash
A98: ORD-1097 | B98: 2024-06-06 | C98: 2024-06-09 | D98: Sara Khan | E98: Consumer | F98: East | G98: Washington | H98: Seattle | I98: Furniture | J98: Chairs | K98: Office Chair | L98: 4 | M98: 408.42 | N98: 0.1 | O98: 1470.31 | P98: -27.19 | Q98: Second Class | R98: Cash
A99: ORD-1098 | B99: 2023-06-06 | C99: 2023-06-14 | D99: Dev Mehta | E99: Home Office | F99: Central | G99: Washington | H99: Seattle | I99: Technology | J99: Phones | K99: Desk Phone | L99: 3 | M99: 428.47 | N99: 0.3 | O99: 899.79 | P99: 42.55 | Q99: Same Day | R99: Card
A100: ORD-1099 | B100: 2024-03-28 | C100: 2024-04-02 | D100: Ishaan Verma | E100: Corporate | F100: West | G100: Washington | H100: Spokane | I100: Office Supplies | J100: Paper | K100: A4 Paper | L100: 5 | M100: 269.41 | N100: 0.1 | O100: 1212.35 | P100: 64.71 | Q100: First Class | R100: Bank Transfer
A101: ORD-1100 | B101: 2024-10-22 | C101: 2024-10-23 | D101: Ishaan Verma | E101: Home Office | F101: East | G101: California | H101: San Francisco | I101: Furniture | J101: Chairs | K101: Office Chair | L101: 7 | M101: 212.52 | N101: 0.2 | O101: 1190.11 | P101: 308.17 | Q101: Same Day | R101: Cash
A102: ORD-1101 | B102: 2024-04-06 | C102: 2024-04-14 | D102: Ishaan Verma | E102: Home Office | F102: East | G102: California | H102: San Diego | I102: Furniture | J102: Chairs | K102: Office Chair | L102: 2 | M102: 231.01 | N102: 0.05 | O102: 438.92 | P102: -71.1 | Q102: First Class | R102: Bank Transfer
... A120: ORD-1119 | B120: 2023-02-13 | C120: 2023-02-20 | D120: Dev Mehta | E120: Home Office | F120: East | G120: Washington | H120: Spokane | I120: Office Supplies | J120: Paper | K120: A4 Paper | L120: 7 | M120: 129.35 | N120: 0 | O120: 905.45 | P120: -131.73 | Q120: Second Class | R120: Digital Wallet
A121: ORD-1120 | B121: 2023-05-10 | C121: 2023-05-13 | D121: Ishaan Verma | E121: Corporate | F121: Central | G121: California | H121: Los Angeles | I121: Furniture | J121: Chairs | K121: Office Chair | L121: 6 | M121: 168.07 | O121: 806.74 | P121: -133.19 | Q121: Standard Class | R121: Cash
A122: ORD-1121 | B122: 2024-01-11 | C122: 2024-01-14 | D122: Ishaan Verma | E122: Home Office | F122: South | G122: Florida | H122: Orlando | I122: Technology | J122: Phones | K122: Wireless Phone | L122: 5 | M122: 118.33 | N122: 0 | O122: 591.65 | P122: -99.44 | Q122: Standard Class | R122: Bank Transfer
A123: ORD-1122 | B123: 2024-12-21 | C123: 2024-12-24 | D123: Meera Patel | E123: Corporate | F123: East | G123: Florida | H123: Miami | I123: Office Supplies | J123: Binders | K123: File Binder | L123: 5 | M123: 314.74 | N123: 0.15 | O123: 1337.64 | P123: -117.6 | Q123: Same Day | R123: Card
A124: ORD-1123 | B124: 2023-11-24 | C124: 2023-11-27 | D124: Kabir Joshi | E124: Corporate | F124: East | G124: Washington | H124: Spokane | I124: Technology | J124: Accessories | K124: Keyboard | L124: 2 | M124: 251.1 | N124: 0.1 | O124: 451.98 | P124: 103.96 | Q124: Second Class | R124: Cash
A125: ORD-1124 | B125: 2024-05-20 | C125: 2024-05-22 | D125: Meera Patel | E125: Corporate | F125: South | G125: California | H125: San Diego | I125: Furniture | J125: Tables | K125: Side Table | L125: 6 | M125: 214.59 | N125: 0.2 | O125: 1030.03 | P125: -123.92 | Q125: Same Day | R125: Digital Wallet
A126: ORD-1125 | B126: 2024-08-11 | C126: 2024-08-20 | D126: Dev Mehta | E126: Consumer | F126: East | G126: California | H126: Los Angeles | I126: Office Supplies | J126: Paper | K126: A4 Paper | L126: 6 | M126: 291.91 | N126: 0.15 | O126: 1488.74 | P126: 51.04 | Q126: Same Day | R126: Card
...

Sheet Retailed_Data
A1: Order ID | B1: Order Date | C1: Ship Date | D1: Customer Name | E1: Segment | F1: Region | G1: Region_Cleaned | H1: State | I1: City | J1: Category | K1: Sub-Category | L1: Product Name | M1: Quantity | N1: Quantity_Cleaned | O1: Unit Price | P1: Discount | Q1: Sales | R1: Sales_cleaned | S1: Profit | T1: Ship Mode | U1: Payment Type
A2: ORD-1001 | B2: 45041 | C2: 2023-05-04 | D2: Meera Patel | E2: Home Office | F2: South | G2: =IF(TRIM(F2)="","",PROPER(TRIM(F2))) -> South | H2: California | I2: San Francisco | J2: Technology | K2: Accessories | L2: Keyboard | M2: 5 | N2: =IFERROR(IF(TRIM(M2)="","",IF(UPPER(TRIM(M2))="N/A","",IF(VALUE(M2)<0,"",VALUE(M2)))),"") -> 5 | O2: 116.24 | P2: 0.05 | Q2: 552.14 | R2: =IFERROR(IF(Q2<>"",Q2,IF(OR(M2="",O2="",P2=""),"",IF(OR(M2<=0,O2<=0,P2<0,P2>1),"",ROUND(M2*O2*(1-P2),2)))),"") -> 552.14 | S2: 87.67 | T2: Standard Class | U2: Card
A3: ORD-1002 | B3: 45165 | C3: 2023-09-05 | D3: Anaya Rao | E3: Consumer | F3: South | G3: =IF(TRIM(F3)="","",PROPER(TRIM(F3))) -> South | H3: Illinois | I3: Peoria | J3: Furniture | K3: Tables | L3: Side Table | M3: 1 | N3: =IFERROR(IF(TRIM(M3)="","",IF(UPPER(TRIM(M3))="N/A","",IF(VALUE(M3)<0,"",VALUE(M3)))),"") -> 1 | O3: 256.07 | P3: 0.3 | Q3: 179.25 | R3: =IFERROR(IF(Q3<>"",Q3,IF(OR(M3="",O3="",P3=""),"",IF(OR(M3<=0,O3<=0,P3<0,P3>1),"",ROUND(M3*O3*(1-P3),2)))),"") -> 179.25 | S3: 21.32 | T3: First Class | U3: Card
A4: ORD-1003 | B4: 45641 | C4: 2024-12-22 | D4: Meera Patel | E4: Corporate | F4: Central | G4: =IF(TRIM(F4)="","",PROPER(TRIM(F4))) -> Central | H4: Florida | I4: Orlando | J4: Furniture | K4: Tables | L4: Side Table | M4: 5 | N4: =IFERROR(IF(TRIM(M4)="","",IF(UPPER(TRIM(M4))="N/A","",IF(VALUE(M4)<0,"",VALUE(M4)))),"") -> 5 | O4: 76.72 | P4: 0.1 | Q4: 345.24 | R4: =IFERROR(IF(Q4<>"",Q4,IF(OR(M4="",O4="",P4=""),"",IF(OR(M4<=0,O4<=0,P4<0,P4>1),"",ROUND(M4*O4*(1-P4),2)))),"") -> 345.24 | S4: -45.91 | T4: First Class | U4: Card
A5: ORD-1004 | B5: 45397 | C5: 2024-04-21 | D5: Sara Khan | E5: Home Office | F5: West | G5: =IF(TRIM(F5)="","",PROPER(TRIM(F5))) -> West | H5: Illinois | I5: Chicago | J5: Technology | K5: Accessories | L5: Keyboard | M5: 7 | N5: =IFERROR(IF(TRIM(M5)="","",IF(UPPER(TRIM(M5))="N/A","",IF(VALUE(M5)<0,"",VALUE(M5)))),"") -> 7 | O5: 42.83 | P5: 0.1 | Q5: 269.83 | R5: =IFERROR(IF(Q5<>"",Q5,IF(OR(M5="",O5="",P5=""),"",IF(OR(M5<=0,O5<=0,P5<0,P5>1),"",ROUND(M5*O5*(1-P5),2)))),"") -> 269.83 | S5: 54.38 | T5: Second Class | U5: Bank Transfer
A6: ORD-1005 | B6: 45165 | C6: 2023-09-02 | D6: Sara Khan | E6: Home Office | F6: Central | G6: =IF(TRIM(F6)="","",PROPER(TRIM(F6))) -> Central | H6: California | I6: San Diego | J6: Furniture | K6: Chairs | L6: Visitor Chair | M6: 5 | N6: =IFERROR(IF(TRIM(M6)="","",IF(UPPER(TRIM(M6))="N/A","",IF(VALUE(M6)<0,"",VALUE(M6)))),"") -> 5 | O6: 208.41 | P6: 0.1 | Q6: 937.85 | R6: =IFERROR(IF(Q6<>"",Q6,IF(OR(M6="",O6="",P6=""),"",IF(OR(M6<=0,O6<=0,P6<0,P6>1),"",ROUND(M6*O6*(1-P6),2)))),"") -> 937.85 | S6: -98.64 | T6: Standard Class | U6: Cash
A7: ORD-1006 | B7: 45177 | C7: 2023-09-12 | D7: Dev Mehta | E7: Consumer | F7: East | G7: =IF(TRIM(F7)="","",PROPER(TRIM(F7))) -> East | H7: New York | I7: Buffalo | J7: Technology | K7: Phones | L7: Desk Phone | M7: 7 | N7: =IFERROR(IF(TRIM(M7)="","",IF(UPPER(TRIM(M7))="N/A","",IF(VALUE(M7)<0,"",VALUE(M7)))),"") -> 7 | O7: 127.32 | P7: 0.3 | Q7: 623.87 | R7: =IFERROR(IF(Q7<>"",Q7,IF(OR(M7="",O7="",P7=""),"",IF(OR(M7<=0,O7<=0,P7<0,P7>1),"",ROUND(M7*O7*(1-P7),2)))),"") -> 623.87 | S7: 85.19 | T7: First Class | U7: Digital Wallet
A8: ORD-1007 | B8: 44994 | C8: 2023-03-17 | D8: Kabir Joshi | E8: Corporate | F8: East | G8: =IF(TRIM(F8)="","",PROPER(TRIM(F8))) -> East | H8: New York | I8: Albany | J8: Office Supplies | K8: Binders | L8: Ring Binder | M8: 6 | N8: =IFERROR(IF(TRIM(M8)="","",IF(UPPER(TRIM(M8))="N/A","",IF(VALUE(M8)<0,"",VALUE(M8)))),"") -> 6 | O8: 101.98 | P8: 0.15 | Q8: 520.1 | R8: =IFERROR(IF(Q8<>"",Q8,IF(OR(M8="",O8="",P8=""),"",IF(OR(M8<=0,O8<=0,P8<0,P8>1),"",ROUND(M8*O8*(1-P8),2)))),"") -> 520.1 | S8: 1.04 | T8: First Class | U8: Digital Wallet
A9: ORD-1008 | B9: 45335 | C9: 2024-02-15 | E9: Home Office | F9: East | G9: =IF(TRIM(F9)="","",PROPER(TRIM(F9))) -> East | H9: Texas | I9: Houston | J9: Technology | K9: Phones | L9: Wireless Phone | M9: 3 | N9: =IFERROR(IF(TRIM(M9)="","",IF(UPPER(TRIM(M9))="N/A","",IF(VALUE(M9)<0,"",VALUE(M9)))),"") -> 3 | O9: 233.21 | P9: 0 | Q9: 699.63 | R9: =IFERROR(IF(Q9<>"",Q9,IF(OR(M9="",O9="",P9=""),"",IF(OR(M9<=0,O9<=0,P9<0,P9>1),"",ROUND(M9*O9*(1-P9),2)))),"") -> 699.63 | S9: 117.3 | T9: Same Day | U9: Card
A10: ORD-1009 | B10: 45317 | C10: 2024-01-28 | D10: Riya Desai | E10: Home Office | F10: Central | G10: =IF(TRIM(F10)="","",PROPER(TRIM(F10))) -> Central | H10: Illinois | I10: Springfield | J10: Office Supplies | K10: Paper | L10: A4 Paper | M10: 5 | N10: =IFERROR(IF(TRIM(M10)="","",IF(UPPER(TRIM(M10))="N/A","",IF(VALUE(M10)<0,"",VALUE(M10)))),"") -> 5 | O10: 437.22 | P10: 0 | Q10: 2186.1 | R10: =IFERROR(IF(Q10<>"",Q10,IF(OR(M10="",O10="",P10=""),"",IF(OR(M10<=0,O10<=0,P10<0,P10>1),"",ROUND(M10*O10*(1-P10),2)))),"") -> 2186.1 | S10: 290.6 | T10: First Class | U10: Digital Wallet
A11: ORD-1010 | B11: 45391 | C11: 2024-04-11 | D11: Riya Desai | E11: Home Office | F11: East | G11: =IF(TRIM(F11)="","",PROPER(TRIM(F11))) -> East | H11: California | I11: San Francisco | J11: Furniture | K11: Tables | L11: Office Table | M11: 5 | N11: =IFERROR(IF(TRIM(M11)="","",IF(UPPER(TRIM(M11))="N/A","",IF(VALUE(M11)<0,"",VALUE(M11)))),"") -> 5 | O11: 437.57 | P11: 0.05 | Q11: 2078.46 | R11: =IFERROR(IF(Q11<>"",Q11,IF(OR(M11="",O11="",P11=""),"",IF(OR(M11<=0,O11<=0,P11<0,P11>1),"",ROUND(M11*O11*(1-P11),2)))),"") -> 2078.46 | S11: 111.27 | T11: First Class | U11: Cash
A12: ORD-1011 | B12: 45470 | C12: 2024-07-02 | D12: Sara Khan | E12: Consumer | F12: East | G12: =IF(TRIM(F12)="","",PROPER(TRIM(F12))) -> East | H12: California | I12: San Francisco | J12: Technology | K12: Phones | L12: Wireless Phone | M12: 6 | N12: =IFERROR(IF(TRIM(M12)="","",IF(UPPER(TRIM(M12))="N/A","",IF(VALUE(M12)<0,"",VALUE(M12)))),"") -> 6 | O12: 223.96 | P12: 0 | Q12: 1343.76 | R12: =IFERROR(IF(Q12<>"",Q12,IF(OR(M12="",O12="",P12=""),"",IF(OR(M12<=0,O12<=0,P12<0,P12>1),"",ROUND(M12*O12*(1-P12),2)))),"") -> 1343.76 | S12: 332.43 | T12: Standard Class | U12: Card
A13: ORD-1012 | B13: 45424 | C13: 2024-05-15 | D13: Riya Desai | E13: Home Office | F13: South | G13: =IF(TRIM(F13)="","",PROPER(TRIM(F13))) -> South | H13: California | I13: San Francisco | J13: Technology | K13: Accessories | L13: Keyboard | M13: 3 | N13: =IFERROR(IF(TRIM(M13)="","",IF(UPPER(TRIM(M13))="N/A","",IF(VALUE(M13)<0,"",VALUE(M13)))),"") -> 3 | O13: 64.75 | P13: 0.15 | Q13: 165.11 | R13: =IFERROR(IF(Q13<>"",Q13,IF(OR(M13="",O13="",P13=""),"",IF(OR(M13<=0,O13<=0,P13<0,P13>1),"",ROUND(M13*O13*(1-P13),2)))),"") -> 165.11 | S13: 42.19 | T13: Second Class | U13: Bank Transfer
A14: ORD-1013 | B14: 45614 | C14: 2024-11-22 | D14: Meera Patel | E14: Corporate | F14: West | G14: =IF(TRIM(F14)="","",PROPER(TRIM(F14))) -> West | H14: Washington | I14: Spokane | J14: Office Supplies | K14: Paper | L14: Copy Paper | M14: 8 | N14: =IFERROR(IF(TRIM(M14)="","",IF(UPPER(TRIM(M14))="N/A","",IF(VALUE(M14)<0,"",VALUE(M14)))),"") -> 8 | O14: 405.63 | P14: 0.15 | Q14: 2758.28 | R14: =IFERROR(IF(Q14<>"",Q14,IF(OR(M14="",O14="",P14=""),"",IF(OR(M14<=0,O14<=0,P14<0,P14>1),"",ROUND(M14*O14*(1-P14),2)))),"") -> 2758.28 | S14: -342.96 | T14: Second Class | U14: Cash
A15: ORD-1014 | B15: 44999 | C15: 2023-03-16 | D15: Sara Khan | E15: Corporate | F15: West | G15: =IF(TRIM(F15)="","",PROPER(TRIM(F15))) -> West | H15: Washington | I15: Tacoma | J15: Furniture | K15: Chairs | L15: Ergo Chair | M15: 1 | N15: =IFERROR(IF(TRIM(M15)="","",IF(UPPER(TRIM(M15))="N/A","",IF(VALUE(M15)<0,"",VALUE(M15)))),"") -> 1 | O15: 109.19 | P15: 0 | Q15: 109.19 | R15: =IFERROR(IF(Q15<>"",Q15,IF(OR(M15="",O15="",P15=""),"",IF(OR(M15<=0,O15<=0,P15<0,P15>1),"",ROUND(M15*O15*(1-P15),2)))),"") -> 109.19 | S15: 23.52 | T15: Second Class | U15: Digital Wallet
A16: ORD-1015 | B16: 45411 | C16: 2024-05-06 | D16: Ishaan Verma | E16: Home Office | F16: West | G16: =IF(TRIM(F16)="","",PROPER(TRIM(F16))) -> West | H16: Florida | I16: Miami | J16: Furniture | K16: Tables | L16: Side Table | M16: 2 | N16: =IFERROR(IF(TRIM(M16)="","",IF(UPPER(TRIM(M16))="N/A","",IF(VALUE(M16)<0,"",VALUE(M16)))),"") -> 2 | O16: 50.84 | P16: 0.15 | Q16: 86.43 | R16: =IFERROR(IF(Q16<>"",Q16,IF(OR(M16="",O16="",P16=""),"",IF(OR(M16<=0,O16<=0,P16<0,P16>1),"",ROUND(M16*O16*(1-P16),2)))),"") -> 86.43 | S16: -1.47 | T16: Standard Class | U16: Card
A17: ORD-1016 | B17: 45274 | C17: 2023-12-17 | D17: Riya Desai | E17: Corporate | F17: East | G17: =IF(TRIM(F17)="","",PROPER(TRIM(F17))) -> East | H17: California | I17: Los Angeles | J17: Office Supplies | K17: Paper | L17: A4 Paper | M17: 4 | N17: =IFERROR(IF(TRIM(M17)="","",IF(UPPER(TRIM(M17))="N/A","",IF(VALUE(M17)<0,"",VALUE(M17)))),"") -> 4 | O17: 92.07 | P17: 0.15 | Q17: 313.04 | R17: =IFERROR(IF(Q17<>"",Q17,IF(OR(M17="",O17="",P17=""),"",IF(OR(M17<=0,O17<=0,P17<0,P17>1),"",ROUND(M17*O17*(1-P17),2)))),"") -> 313.04 | S17: -36.16 | T17: Same Day | U17: Card
A18: ORD-1017 | B18: 45594 | C18: 2024-11-06 | D18: Ishaan Verma | E18: Consumer | F18: South | G18: =IF(TRIM(F18)="","",PROPER(TRIM(F18))) -> South | H18: Illinois | I18: Chicago | J18: Furniture | K18: Chairs | L18: Ergo Chair | M18: 2 | N18: =IFERROR(IF(TRIM(M18)="","",IF(UPPER(TRIM(M18))="N/A","",IF(VALUE(M18)<0,"",VALUE(M18)))),"") -> 2 | O18: 417.45 | P18: 0.05 | Q18: 793.15 | R18: =IFERROR(IF(Q18<>"",Q18,IF(OR(M18="",O18="",P18=""),"",IF(OR(M18<=0,O18<=0,P18<0,P18>1),"",ROUND(M18*O18*(1-P18),2)))),"") -> 793.15 | S18: -82.09 | T18: Second Class | U18: Digital Wallet
A19: ORD-1018 | B19: 45326 | C19: 2024-02-13 | D19: Ishaan Verma | E19: Consumer | F19: East | G19: =IF(TRIM(F19)="","",PROPER(TRIM(F19))) -> East | H19: Texas | I19: Dallas | J19: Furniture | K19: Chairs | L19: Office Chair | M19: 5 | N19: =IFERROR(IF(TRIM(M19)="","",IF(UPPER(TRIM(M19))="N/A","",IF(VALUE(M19)<0,"",VALUE(M19)))),"") -> 5 | O19: 194.97 | P19: 0.3 | Q19: 682.39 | R19: =IFERROR(IF(Q19<>"",Q19,IF(OR(M19="",O19="",P19=""),"",IF(OR(M19<=0,O19<=0,P19<0,P19>1),"",ROUND(M19*O19*(1-P19),2)))),"") -> 682.39 | S19: 189.63 | T19: Second Class | U19: Card
A20: ORD-1019 | B20: 45482 | C20: 2024-07-18 | D20: Kabir Joshi | E20: Consumer | F20: West | G20: =IF(TRIM(F20)="","",PROPER(TRIM(F20))) -> West | H20: California | I20: San Francisco | J20: Technology | K20: Phones | L20: Desk Phone | N20: =IFERROR(IF(TRIM(M20)="","",IF(UPPER(TRIM(M20))="N/A","",IF(VALUE(M20)<0,"",VALUE(M20)))),"") | O20: 33.27 | P20: 0.2 | Q20: 159.7 | R20: =IFERROR(IF(Q20<>"",Q20,IF(OR(M20="",O20="",P20=""),"",IF(OR(M20<=0,O20<=0,P20<0,P20>1),"",ROUND(M20*O20*(1-P20),2)))),"") -> 159.7 | S20: 6.28 | T20: Standard Class | U20: Card
A21: ORD-1020 | B21: 45167 | C21: 2023-09-05 | D21: Dev Mehta | E21: Corporate | F21: East | G21: =IF(TRIM(F21)="","",PROPER(TRIM(F21))) -> East | H21: Florida | I21: Miami | J21: Technology | K21: Accessories | L21: Webcam | M21: 4 | N21: =IFERROR(IF(TRIM(M21)="","",IF(UPPER(TRIM(M21))="N/A","",IF(VALUE(M21)<0,"",VALUE(M21)))),"") -> 4 | O21: 263.88 | P21: 0 | Q21: 1055.52 | R21: =IFERROR(IF(Q21<>"",Q21,IF(OR(M21="",O21="",P21=""),"",IF(OR(M21<=0,O21<=0,P21<0,P21>1),"",ROUND(M21*O21*(1-P21),2)))),"") -> 1055.52 | S21: 110.74 | T21: First Class | U21: Cash
A22: ORD-1021 | B22: 45332 | C22: 2024-02-12 | D22: Meera Patel | E22: Home Office | F22: East | G22: =IF(TRIM(F22)="","",PROPER(TRIM(F22))) -> East | H22: New York | I22: Albany | J22: Office Supplies | K22: Binders | L22: File Binder | M22: 5 | N22: =IFERROR(IF(TRIM(M22)="","",IF(UPPER(TRIM(M22))="N/A","",IF(VALUE(M22)<0,"",VALUE(M22)))),"") -> 5 | O22: 210.09 | P22: 0 | Q22: 1050.45 | R22: =IFERROR(IF(Q22<>"",Q22,IF(OR(M22="",O22="",P22=""),"",IF(OR(M22<=0,O22<=0,P22<0,P22>1),"",ROUND(M22*O22*(1-P22),2)))),"") -> 1050.45 | S22: -184.58 | T22: First Class | U22: Cash
A23: ORD-1022 | B23: 44997 | C23: 2023-03-21 | D23: Aarav Shah | E23: Home Office | F23: Central | G23: =IF(TRIM(F23)="","",PROPER(TRIM(F23))) -> Central | H23: New York | I23: Buffalo | J23: Office Supplies | K23: Binders | L23: File Binder | M23: 5 | N23: =IFERROR(IF(TRIM(M23)="","",IF(UPPER(TRIM(M23))="N/A","",IF(VALUE(M23)<0,"",VALUE(M23)))),"") -> 5 | O23: 77.72 | P23: 0.2 | Q23: 310.88 | R23: =IFERROR(IF(Q23<>"",Q23,IF(OR(M23="",O23="",P23=""),"",IF(OR(M23<=0,O23<=0,P23<0,P23>1),"",ROUND(M23*O23*(1-P23),2)))),"") -> 310.88 | S23: 44.65 | T23: Standard Class | U23: Cash
A24: ORD-1023 | B24: 45045 | C24: 2023-05-05 | D24: Sara Khan | E24: Home Office | G24: Unknown | H24: California | I24: San Francisco | J24: Office Supplies | K24: Binders | L24: File Binder | M24: 3 | N24: =IFERROR(IF(TRIM(M24)="","",IF(UPPER(TRIM(M24))="N/A","",IF(VALUE(M24)<0,"",VALUE(M24)))),"") -> 3 | O24: 128.38 | P24: 0.2 | Q24: 308.11 | R24: =IFERROR(IF(Q24<>"",Q24,IF(OR(M24="",O24="",P24=""),"",IF(OR(M24<=0,O24<=0,P24<0,P24>1),"",ROUND(M24*O24*(1-P24),2)))),"") -> 308.11 | S24: -25.61 | T24: Same Day | U24: Bank Transfer
A25: ORD-1024 | B25: 45021 | C25: 2023-04-10 | D25: Kabir Joshi | E25: Home Office | F25: South | G25: =IF(TRIM(F25)="","",PROPER(TRIM(F25))) -> South | H25: Washington | I25: Spokane | J25: Furniture | K25: Chairs | L25: Visitor Chair | M25: 5 | N25: =IFERROR(IF(TRIM(M25)="","",IF(UPPER(TRIM(M25))="N/A","",IF(VALUE(M25)<0,"",VALUE(M25)))),"") -> 5 | O25: 27.49 | P25: 0.1 | Q25: 123.7 | R25: =IFERROR(IF(Q25<>"",Q25,IF(OR(M25="",O25="",P25=""),"",IF(OR(M25<=0,O25<=0,P25<0,P25>1),"",ROUND(M25*O25*(1-P25),2)))),"") -> 123.7 | S25: 21.61 | T25: Same Day | U25: Card
A26: ORD-1025 | B26: 45004 | C26: 2023-03-26 | D26: Kabir Joshi | E26: Consumer | F26: Central | G26: =IF(TRIM(F26)="","",PROPER(TRIM(F26))) -> Central | H26: Washington | I26: Seattle | J26: Furniture | K26: Chairs | L26: Office Chair | M26: 1 | N26: =IFERROR(IF(TRIM(M26)="","",IF(UPPER(TRIM(M26))="N/A","",IF(VALUE(M26)<0,"",VALUE(M26)))),"") -> 1 | O26: 376.89 | P26: 0.2 | Q26: 301.51 | R26: =IFERROR(IF(Q26<>"",Q26,IF(OR(M26="",O26="",P26=""),"",IF(OR(M26<=0,O26<=0,P26<0,P26>1),"",ROUND(M26*O26*(1-P26),2)))),"") -> 301.51 | S26: 22.36 | T26: Standard Class | U26: Bank Transfer
A27: ORD-1026 | B27: 45625 | C27: 2024-12-06 | D27: Kabir Joshi | E27: Consumer | F27: East | G27: =IF(TRIM(F27)="","",PROPER(TRIM(F27))) -> East | H27: New York | I27: Albany | J27: Furniture | K27: Tables | L27: Office Table | M27: 2 | N27: =IFERROR(IF(TRIM(M27)="","",IF(UPPER(TRIM(M27))="N/A","",IF(VALUE(M27)<0,"",VALUE(M27)))),"") -> 2 | O27: 164.33 | P27: 0.2 | Q27: 262.93 | R27: =IFERROR(IF(Q27<>"",Q27,IF(OR(M27="",O27="",P27=""),"",IF(OR(M27<=0,O27<=0,P27<0,P27>1),"",ROUND(M27*O27*(1-P27),2)))),"") -> 262.93 | S27: 59.61 | T27: Same Day | U27: Card
A28: ORD-1027 | B28: 45267 | C28: 2023-12-08 | D28: Ishaan Verma | E28: Consumer | F28: East | G28: =IF(TRIM(F28)="","",PROPER(TRIM(F28))) -> East | H28: Florida | I28: Tampa | J28: Furniture | K28: Tables | L28: Conference Table | M28: 4 | N28: =IFERROR(IF(TRIM(M28)="","",IF(UPPER(TRIM(M28))="N/A","",IF(VALUE(M28)<0,"",VALUE(M28)))),"") -> 4 | O28: 125.93 | P28: 0.3 | Q28: 352.6 | R28: =IFERROR(IF(Q28<>"",Q28,IF(OR(M28="",O28="",P28=""),"",IF(OR(M28<=0,O28<=0,P28<0,P28>1),"",ROUND(M28*O28*(1-P28),2)))),"") -> 352.6 | S28: -45.94 | T28: First Class | U28: Bank Transfer
A29: ORD-1028 | B29: 45155 | C29: 2023-08-22 | D29: Dev Mehta | E29: Home Office | F29: South | G29: =IF(TRIM(F29)="","",PROPER(TRIM(F29))) -> South | H29: California | I29: San Francisco | J29: Furniture | K29: Tables | L29: Side Table | M29: 4 | N29: =IFERROR(IF(TRIM(M29)="","",IF(UPPER(TRIM(M29))="N/A","",IF(VALUE(M29)<0,"",VALUE(M29)))),"") -> 4 | O29: 184.12 | P29: 0.1 | Q29: 662.83 | R29: =IFERROR(IF(Q29<>"",Q29,IF(OR(M29="",O29="",P29=""),"",IF(OR(M29<=0,O29<=0,P29<0,P29>1),"",ROUND(M29*O29*(1-P29),2)))),"") -> 662.83 | S29: 144.23 | T29: First Class | U29: Card
A30: ORD-1029 | B30: 45194 | C30: 2023-10-01 | D30: Anaya Rao | E30: Home Office | F30: West | G30: =IF(TRIM(F30)="","",PROPER(TRIM(F30))) -> West | H30: New York | I30: Albany | J30: Furniture | K30: Chairs | L30: Office Chair | M30: 5 | N30: =IFERROR(IF(TRIM(M30)="","",IF(UPPER(TRIM(M30))="N/A","",IF(VALUE(M30)<0,"",VALUE(M30)))),"") -> 5 | O30: 24.91 | P30: 0.2 | Q30: 99.64 | R30: =IFERROR(IF(Q30<>"",Q30,IF(OR(M30="",O30="",P30=""),"",IF(OR(M30<=0,O30<=0,P30<0,P30>1),"",ROUND(M30*O30*(1-P30),2)))),"") -> 99.64 | S30: 1.98 | T30: Second Class | U30: Bank Transfer
A31: ORD-1030 | B31: 45652 | C31: 2025-01-01 | D31: Dev Mehta | E31: Home Office | F31: West | G31: =IF(TRIM(F31)="","",PROPER(TRIM(F31))) -> West | H31: Florida | I31: Miami | J31: Furniture | K31: Chairs | L31: Visitor Chair | M31: 4 | N31: =IFERROR(IF(TRIM(M31)="","",IF(UPPER(TRIM(M31))="N/A","",IF(VALUE(M31)<0,"",VALUE(M31)))),"") -> 4 | P31: 0 | Q31: 675.96 | R31: =IFERROR(IF(Q31<>"",Q31,IF(OR(M31="",O31="",P31=""),"",IF(OR(M31<=0,O31<=0,P31<0,P31>1),"",ROUND(M31*O31*(1-P31),2)))),"") -> 675.96 | S31: 173.37 | T31: First Class | U31: Bank Transfer
A32: ORD-1031 | B32: 45345 | C32: 2024-03-01 | D32: Kabir Joshi | E32: Home Office | F32: Central | G32: =IF(TRIM(F32)="","",PROPER(TRIM(F32))) -> Central | H32: Texas | I32: Dallas | J32: Technology | K32: Accessories | L32: Mouse | M32: 5 | N32: =IFERROR(IF(TRIM(M32)="","",IF(UPPER(TRIM(M32))="N/A","",IF(VALUE(M32)<0,"",VALUE(M32)))),"") -> 5 | O32: 253.05 | P32: 0.05 | Q32: 1201.99 | R32: =IFERROR(IF(Q32<>"",Q32,IF(OR(M32="",O32="",P32=""),"",IF(OR(M32<=0,O32<=0,P32<0,P32>1),"",ROUND(M32*O32*(1-P32),2)))),"") -> 1201.99 | S32: 16.11 | T32: Standard Class | U32: Bank Transfer
A33: ORD-1032 | B33: 45142 | C33: 2023-08-13 | D33: Ishaan Verma | E33: Home Office | F33: East | G33: =IF(TRIM(F33)="","",PROPER(TRIM(F33))) -> East | H33: Florida | I33: Tampa | J33: Office Supplies | K33: Binders | L33: File Binder | M33: 6 | N33: =IFERROR(IF(TRIM(M33)="","",IF(UPPER(TRIM(M33))="N/A","",IF(VALUE(M33)<0,"",VALUE(M33)))),"") -> 6 | O33: 213.52 | P33: 0.15 | Q33: 1088.95 | R33: =IFERROR(IF(Q33<>"",Q33,IF(OR(M33="",O33="",P33=""),"",IF(OR(M33<=0,O33<=0,P33<0,P33>1),"",ROUND(M33*O33*(1-P33),2)))),"") -> 1088.95 | S33: 142.42 | T33: Standard Class | U33: Bank Transfer
A34: ORD-1033 | B34: 45606 | C34: 2024-11-14 | D34: Sara Khan | E34: Consumer | F34: West | G34: =IF(TRIM(F34)="","",PROPER(TRIM(F34))) -> West | H34: Washington | I34: Tacoma | J34: Technology | K34: Phones | L34: Desk Phone | M34: 6 | N34: =IFERROR(IF(TRIM(M34)="","",IF(UPPER(TRIM(M34))="N/A","",IF(VALUE(M34)<0,"",VALUE(M34)))),"") -> 6 | O34: 49.28 | P34: 0.05 | Q34: 280.9 | R34: =IFERROR(IF(Q34<>"",Q34,IF(OR(M34="",O34="",P34=""),"",IF(OR(M34<=0,O34<=0,P34<0,P34>1),"",ROUND(M34*O34*(1-P34),2)))),"") -> 280.9 | S34: 36.37 | T34: Second Class | U34: Digital Wallet
A35: ORD-1034 | B35: 45001 | C35: 2023-03-20 | D35: Kabir Joshi | E35: Home Office | F35: West | G35: =IF(TRIM(F35)="","",PROPER(TRIM(F35))) -> West | H35: Florida | I35: Orlando | J35: Technology | K35: Phones | L35: Desk Phone | M35: 4 | N35: =IFERROR(IF(TRIM(M35)="","",IF(UPPER(TRIM(M35))="N/A","",IF(VALUE(M35)<0,"",VALUE(M35)))),"") -> 4 | O35: 325.51 | P35: 0.15 | Q35: 1106.73 | R35: =IFERROR(IF(Q35<>"",Q35,IF(OR(M35="",O35="",P35=""),"",IF(OR(M35<=0,O35<=0,P35<0,P35>1),"",ROUND(M35*O35*(1-P35),2)))),"") -> 1106.73 | S35: 52.47 | T35: Same Day | U35: Cash
A36: ORD-1035 | B36: 45639 | C36: 2024-12-21 | D36: Dev Mehta | E36: Corporate | F36: South | G36: =IF(TRIM(F36)="","",PROPER(TRIM(F36))) -> South | H36: Illinois | I36: Springfield | J36: Furniture | K36: Tables | L36: Side Table | M36: 1 | N36: =IFERROR(IF(TRIM(M36)="","",IF(UPPER(TRIM(M36))="N/A","",IF(VALUE(M36)<0,"",VALUE(M36)))),"") -> 1 | O36: 254.37 | P36: 0 | Q36: 254.37 | R36: =IFERROR(IF(Q36<>"",Q36,IF(OR(M36="",O36="",P36=""),"",IF(OR(M36<=0,O36<=0,P36<0,P36>1),"",ROUND(M36*O36*(1-P36),2)))),"") -> 254.37 | S36: 7.62 | T36: Same Day | U36: Cash
A37: ORD-1036 | B37: 45413 | C37: 2024-05-10 | D37: Ishaan Verma | E37: Home Office | F37: East | G37: =IF(TRIM(F37)="","",PROPER(TRIM(F37))) -> East | H37: Florida | I37: Orlando | J37: Technology | K37: Accessories | L37: Mouse | M37: 4 | N37: =IFERROR(IF(TRIM(M37)="","",IF(UPPER(TRIM(M37))="N/A","",IF(VALUE(M37)<0,"",VALUE(M37)))),"") -> 4 | O37: 379.22 | P37: 0.1 | Q37: 1365.19 | R37: =IFERROR(IF(Q37<>"",Q37,IF(OR(M37="",O37="",P37=""),"",IF(OR(M37<=0,O37<=0,P37<0,P37>1),"",ROUND(M37*O37*(1-P37),2)))),"") -> 1365.19 | S37: 235.19 | T37: Same Day | U37: Card
A38: ORD-1037 | B38: 45219 | C38: 2023-10-23 | D38: Sara Khan | E38: Corporate | F38: East | G38: =IF(TRIM(F38)="","",PROPER(TRIM(F38))) -> East | H38: New York | I38: Buffalo | J38: Technology | K38: Accessories | L38: Webcam | M38: 6 | N38: =IFERROR(IF(TRIM(M38)="","",IF(UPPER(TRIM(M38))="N/A","",IF(VALUE(M38)<0,"",VALUE(M38)))),"") -> 6 | O38: 149.31 | P38: 0.2 | Q38: 716.69 | R38: =IFERROR(IF(Q38<>"",Q38,IF(OR(M38="",O38="",P38=""),"",IF(OR(M38<=0,O38<=0,P38<0,P38>1),"",ROUND(M38*O38*(1-P38),2)))),"") -> 716.69 | S38: -102.44 | T38: Second Class | U38: Card
A39: ORD-1038 | B39: 45344 | C39: 2024-02-29 | D39: Aarav Shah | E39: Home Office | F39: South | G39: =IF(TRIM(F39)="","",PROPER(TRIM(F39))) -> South | H39: Texas | I39: Austin | J39: Office Supplies | K39: Paper | L39: Notebook Paper | M39: 8 | N39: =IFERROR(IF(TRIM(M39)="","",IF(UPPER(TRIM(M39))="N/A","",IF(VALUE(M39)<0,"",VALUE(M39)))),"") -> 8 | O39: 191.77 | P39: 0.05 | Q39: 1457.45 | R39: =IFERROR(IF(Q39<>"",Q39,IF(OR(M39="",O39="",P39=""),"",IF(OR(M39<=0,O39<=0,P39<0,P39>1),"",ROUND(M39*O39*(1-P39),2)))),"") -> 1457.45 | S39: 296.05 | T39: Standard Class | U39: Bank Transfer
A40: ORD-1039 | B40: 45326 | C40: 2024-02-05 | D40: Anaya Rao | E40: Corporate | F40: South | G40: =IF(TRIM(F40)="","",PROPER(TRIM(F40))) -> South | H40: Florida | I40: Tampa | J40: Office Supplies | K40: Binders | L40: File Binder | M40: 4 | N40: =IFERROR(IF(TRIM(M40)="","",IF(UPPER(TRIM(M40))="N/A","",IF(VALUE(M40)<0,"",VALUE(M40)))),"") -> 4 | O40: 223.8 | P40: 0.1 | Q40: 805.68 | R40: =IFERROR(IF(Q40<>"",Q40,IF(OR(M40="",O40="",P40=""),"",IF(OR(M40<=0,O40<=0,P40<0,P40>1),"",ROUND(M40*O40*(1-P40),2)))),"") -> 805.68 | S40: 16.5 | T40: Second Class | U40: Digital Wallet
A41: ORD-1040 | B41: 45564 | C41: 2024-10-06 | D41: Kabir Joshi | E41: Corporate | F41: East | G41: =IF(TRIM(F41)="","",PROPER(TRIM(F41))) -> East | H41: Illinois | I41: Chicago | J41: Furniture | K41: Tables | L41: Office Table | M41: 7 | N41: =IFERROR(IF(TRIM(M41)="","",IF(UPPER(TRIM(M41))="N/A","",IF(VALUE(M41)<0,"",VALUE(M41)))),"") -> 7 | O41: 269.62 | P41: 0.3 | Q41: 1321.14 | R41: =IFERROR(IF(Q41<>"",Q41,IF(OR(M41="",O41="",P41=""),"",IF(OR(M41<=0,O41<=0,P41<0,P41>1),"",ROUND(M41*O41*(1-P41),2)))),"") -> 1321.14 | S41: -221.33 | T41: First Class | U41: Digital Wallet
A42: ORD-1041 | B42: 45143 | C42: 2023-08-12 | D42: Riya Desai | E42: Consumer | F42: South | G42: =IF(TRIM(F42)="","",PROPER(TRIM(F42))) -> South | H42: Florida | I42: Orlando | J42: Office Supplies | K42: Binders | L42: Ring Binder | M42: 6 | N42: =IFERROR(IF(TRIM(M42)="","",IF(UPPER(TRIM(M42))="N/A","",IF(VALUE(M42)<0,"",VALUE(M42)))),"") -> 6 | O42: 344.46 | P42: 0.15 | Q42: 1756.75 | R42: =IFERROR(IF(Q42<>"",Q42,IF(OR(M42="",O42="",P42=""),"",IF(OR(M42<=0,O42<=0,P42<0,P42>1),"",ROUND(M42*O42*(1-P42),2)))),"") -> 1756.75 | S42: -91.35 | T42: Standard Class | U42: Bank Transfer
A43: ORD-1042 | B43: 45592 | D43: Kabir Joshi | E43: Consumer | F43: East | G43: =IF(TRIM(F43)="","",PROPER(TRIM(F43))) -> East | H43: California | I43: San Francisco | J43: Furniture | K43: Tables | L43: Conference Table | M43: 1 | N43: =IFERROR(IF(TRIM(M43)="","",IF(UPPER(TRIM(M43))="N/A","",IF(VALUE(M43)<0,"",VALUE(M43)))),"") -> 1 | O43: 341.37 | P43: 0.05 | Q43: 324.3 | R43: =IFERROR(IF(Q43<>"",Q43,IF(OR(M43="",O43="",P43=""),"",IF(OR(M43<=0,O43<=0,P43<0,P43>1),"",ROUND(M43*O43*(1-P43),2)))),"") -> 324.3 | S43: -28.63 | T43: Standard Class | U43: Cash
A44: ORD-1043 | B44: 45643 | C44: 2024-12-20 | D44: Riya Desai | E44: Consumer | F44: West | G44: =IF(TRIM(F44)="","",PROPER(TRIM(F44))) -> West | H44: Texas | I44: Dallas | J44: Office Supplies | K44: Paper | L44: Notebook Paper | M44: 3 | N44: =IFERROR(IF(TRIM(M44)="","",IF(UPPER(TRIM(M44))="N/A","",IF(VALUE(M44)<0,"",VALUE(M44)))),"") -> 3 | O44: 275.8 | P44: 0.3 | Q44: 579.18 | R44: =IFERROR(IF(Q44<>"",Q44,IF(OR(M44="",O44="",P44=""),"",IF(OR(M44<=0,O44<=0,P44<0,P44>1),"",ROUND(M44*O44*(1-P44),2)))),"") -> 579.18 | S44: 87.13 | T44: Same Day | U44: Digital Wallet
A45: ORD-1044 | B45: 45130 | C45: 2023-07-25 | D45: Aarav Shah | E45: Corporate | F45: South | G45: =IF(TRIM(F45)="","",PROPER(TRIM(F45))) -> South | H45: California | I45: San Francisco | J45: Technology | K45: Accessories | L45: Webcam | M45: 4 | N45: =IFERROR(IF(TRIM(M45)="","",IF(UPPER(TRIM(M45))="N/A","",IF(VALUE(M45)<0,"",VALUE(M45)))),"") -> 4 | O45: 53.04 | P45: 0.1 | Q45: 190.94 | R45: =IFERROR(IF(Q45<>"",Q45,IF(OR(M45="",O45="",P45=""),"",IF(OR(M45<=0,O45<=0,P45<0,P45>1),"",ROUND(M45*O45*(1-P45),2)))),"") -> 190.94 | S45: 40.31 | T45: First Class | U45: Card
A46: ORD-1045 | B46: 45590 | C46: 2024-10-31 | D46: Ishaan Verma | E46: Home Office | F46: East | G46: =IF(TRIM(F46)="","",PROPER(TRIM(F46))) -> East | H46: Texas | I46: Houston | J46: Technology | K46: Phones | L46: Smartphone | M46: 7 | N46: =IFERROR(IF(TRIM(M46)="","",IF(UPPER(TRIM(M46))="N/A","",IF(VALUE(M46)<0,"",VALUE(M46)))),"") -> 7 | O46: 371.47 | P46: 0 | Q46: 2600.29 | R46: =IFERROR(IF(Q46<>"",Q46,IF(OR(M46="",O46="",P46=""),"",IF(OR(M46<=0,O46<=0,P46<0,P46>1),"",ROUND(M46*O46*(1-P46),2)))),"") -> 2600.29 | S46: 50.5 | T46: Second Class | U46: Bank Transfer
A47: ORD-1046 | B47: 45478 | C47: 2024-07-09 | D47: Meera Patel | E47: Corporate | F47: South | G47: =IF(TRIM(F47)="","",PROPER(TRIM(F47))) -> South | H47: Florida | I47: Orlando | J47: Technology | K47: Phones | L47: Desk Phone | M47: 7 | N47: =IFERROR(IF(TRIM(M47)="","",IF(UPPER(TRIM(M47))="N/A","",IF(VALUE(M47)<0,"",VALUE(M47)))),"") -> 7 | O47: 372.97 | P47: 0.2 | Q47: 2088.63 | R47: =IFERROR(IF(Q47<>"",Q47,IF(OR(M47="",O47="",P47=""),"",IF(OR(M47<=0,O47<=0,P47<0,P47>1),"",ROUND(M47*O47*(1-P47),2)))),"") -> 2088.63 | S47: -118.09 | T47: Same Day | U47: Digital Wallet
A48: ORD-1047 | B48: 44956 | C48: 2023-02-05 | D48: Riya Desai | E48: Home Office | F48: Central | G48: =IF(TRIM(F48)="","",PROPER(TRIM(F48))) -> Central | H48: Florida | I48: Orlando | J48: Office Supplies | K48: Binders | L48: File Binder | M48: 3 | N48: =IFERROR(IF(TRIM(M48)="","",IF(UPPER(TRIM(M48))="N/A","",IF(VALUE(M48)<0,"",VALUE(M48)))),"") -> 3 | O48: 223.5 | P48: 0.1 | Q48: 603.45 | R48: =IFERROR(IF(Q48<>"",Q48,IF(OR(M48="",O48="",P48=""),"",IF(OR(M48<=0,O48<=0,P48<0,P48>1),"",ROUND(M48*O48*(1-P48),2)))),"") -> 603.45 | S48: 112.85 | T48: Standard Class | U48: Cash
A49: ORD-1048 | B49: 45174 | C49: 2023-09-13 | D49: Ishaan Verma | E49: Consumer | F49: West | G49: =IF(TRIM(F49)="","",PROPER(TRIM(F49))) -> West | H49: Washington | I49: Spokane | J49: Furniture | K49: Chairs | L49: Office Chair | M49: 8 | N49: =IFERROR(IF(TRIM(M49)="","",IF(UPPER(TRIM(M49))="N/A","",IF(VALUE(M49)<0,"",VALUE(M49)))),"") -> 8 | O49: 253.39 | P49: 0.05 | Q49: 1925.76 | R49: =IFERROR(IF(Q49<>"",Q49,IF(OR(M49="",O49="",P49=""),"",IF(OR(M49<=0,O49<=0,P49<0,P49>1),"",ROUND(M49*O49*(1-P49),2)))),"") -> 1925.76 | S49: 265.14 | T49: Second Class | U49: Digital Wallet
A50: ORD-1049 | B50: 45176 | C50: 2023-09-16 | D50: Dev Mehta | E50: Corporate | F50: South | G50: =IF(TRIM(F50)="","",PROPER(TRIM(F50))) -> South | H50: Texas | I50: Austin | J50: Technology | K50: Accessories | L50: Mouse | M50: 6 | N50: =IFERROR(IF(TRIM(M50)="","",IF(UPPER(TRIM(M50))="N/A","",IF(VALUE(M50)<0,"",VALUE(M50)))),"") -> 6 | O50: 217.18 | P50: 0.2 | Q50: 1042.46 | R50: =IFERROR(IF(Q50<>"",Q50,IF(OR(M50="",O50="",P50=""),"",IF(OR(M50<=0,O50<=0,P50<0,P50>1),"",ROUND(M50*O50*(1-P50),2)))),"") -> 1042.46 | S50: -22.8 | T50: First Class | U50: Bank Transfer
A51: ORD-1050 | B51: 45050 | C51: 2023-05-07 | D51: Sara Khan | E51: Consumer | F51: South | G51: =IF(TRIM(F51)="","",PROPER(TRIM(F51))) -> South | H51: Washington | I51: Seattle | J51: Furniture | K51: Tables | L51: Conference Table | M51: 6 | N51: =IFERROR(IF(TRIM(M51)="","",IF(UPPER(TRIM(M51))="N/A","",IF(VALUE(M51)<0,"",VALUE(M51)))),"") -> 6 | O51: 60.84 | P51: 0.2 | Q51: 292.03 | R51: =IFERROR(IF(Q51<>"",Q51,IF(OR(M51="",O51="",P51=""),"",IF(OR(M51<=0,O51<=0,P51<0,P51>1),"",ROUND(M51*O51*(1-P51),2)))),"") -> 292.03 | S51: 75.17 | T51: First Class | U51: Card
A52: ORD-1051 | B52: 45230 | C52: 2023-11-05 | D52: Aarav Shah | E52: Consumer | F52: Central | G52: =IF(TRIM(F52)="","",PROPER(TRIM(F52))) -> Central | H52: New York | I52: Buffalo | J52: Furniture | K52: Tables | L52: Side Table | M52: 3 | N52: =IFERROR(IF(TRIM(M52)="","",IF(UPPER(TRIM(M52))="N/A","",IF(VALUE(M52)<0,"",VALUE(M52)))),"") -> 3 | O52: 141.6 | P52: 0.3 | Q52: 297.36 | R52: =IFERROR(IF(Q52<>"",Q52,IF(OR(M52="",O52="",P52=""),"",IF(OR(M52<=0,O52<=0,P52<0,P52>1),"",ROUND(M52*O52*(1-P52),2)))),"") -> 297.36 | S52: 19.54 | T52: Second Class | U52: Digital Wallet
A53: ORD-1052 | B53: 44939 | C53: 2023-01-14 | D53: Riya Desai | E53: Corporate | F53: West | G53: =IF(TRIM(F53)="","",PROPER(TRIM(F53))) -> West | H53: Illinois | I53: Springfield | J53: Furniture | K53: Chairs | L53: Ergo Chair | M53: 8 | N53: =IFERROR(IF(TRIM(M53)="","",IF(UPPER(TRIM(M53))="N/A","",IF(VALUE(M53)<0,"",VALUE(M53)))),"") -> 8 | O53: 219.59 | P53: 0.1 | Q53: 1581.05 | R53: =IFERROR(IF(Q53<>"",Q53,IF(OR(M53="",O53="",P53=""),"",IF(OR(M53<=0,O53<=0,P53<0,P53>1),"",ROUND(M53*O53*(1-P53),2)))),"") -> 1581.05 | S53: -150.5 | T53: Same Day | U53: Digital Wallet
A54: ORD-1053 | B54: 45517 | C54: 2024-08-15 | D54: Sara Khan | E54: Consumer | F54: South | G54: =IF(TRIM(F54)="","",PROPER(TRIM(F54))) -> South | H54: Washington | I54: Tacoma | J54: Furniture | K54: Chairs | L54: Visitor Chair | M54: 1 | N54: =IFERROR(IF(TRIM(M54)="","",IF(UPPER(TRIM(M54))="N/A","",IF(VALUE(M54)<0,"",VALUE(M54)))),"") -> 1 | O54: 75.06 | P54: 0.2 | Q54: 60.05 | R54: =IFERROR(IF(Q54<>"",Q54,IF(OR(M54="",O54="",P54=""),"",IF(OR(M54<=0,O54<=0,P54<0,P54>1),"",ROUND(M54*O54*(1-P54),2)))),"") -> 60.05 | S54: 15.41 | T54: Second Class | U54: Digital Wallet
A55: ORD-1054 | B55: 45380 | C55: 2024-03-31 | D55: Sara Khan | E55: Home Office | F55: East | G55: =IF(TRIM(F55)="","",PROPER(TRIM(F55))) -> East | H55: Texas | I55: Austin | J55: Office Supplies | K55: Paper | L55: Notebook Paper | M55: 7 | N55: =IFERROR(IF(TRIM(M55)="","",IF(UPPER(TRIM(M55))="N/A","",IF(VALUE(M55)<0,"",VALUE(M55)))),"") -> 7 | O55: 142.98 | P55: 0.2 | Q55: 800.69 | R55: =IFERROR(IF(Q55<>"",Q55,IF(OR(M55="",O55="",P55=""),"",IF(OR(M55<=0,O55<=0,P55<0,P55>1),"",ROUND(M55*O55*(1-P55),2)))),"") -> 800.69 | S55: -121.94 | T55: Standard Class | U55: Cash
... A65: ORD-1064 | B65: 45122 | C65: 2023-07-22 | D65: Dev Mehta | E65: Home Office | F65: Central | G65: =IF(TRIM(F65)="","",PROPER(TRIM(F65))) -> Central | H65: Illinois | I65: Peoria | J65: Office Supplies | K65: Paper | L65: A4 Paper | M65: 3 | N65: =IFERROR(IF(TRIM(M65)="","",IF(UPPER(TRIM(M65))="N/A","",IF(VALUE(M65)<0,"",VALUE(M65)))),"") -> 3 | O65: 389.9 | P65: 0.1 | Q65: 1052.73 | R65: =IFERROR(IF(Q65<>"",Q65,IF(OR(M65="",O65="",P65=""),"",IF(OR(M65<=0,O65<=0,P65<0,P65>1),"",ROUND(M65*O65*(1-P65),2)))),"") -> 1052.73 | S65: 184.68 | T65: First Class | U65: Bank Transfer
A66: ORD-1065 | B66: 45520 | C66: 2024-08-25 | D66: Anaya Rao | E66: Corporate | F66: Central | G66: =IF(TRIM(F66)="","",PROPER(TRIM(F66))) -> Central | H66: Washington | I66: Spokane | J66: Technology | K66: Phones | L66: Desk Phone | M66: 3 | N66: =IFERROR(IF(TRIM(M66)="","",IF(UPPER(TRIM(M66))="N/A","",IF(VALUE(M66)<0,"",VALUE(M66)))),"") -> 3 | O66: 205.37 | P66: 0.15 | R66: =IFERROR(IF(Q66<>"",Q66,IF(OR(M66="",O66="",P66=""),"",IF(OR(M66<=0,O66<=0,P66<0,P66>1),"",ROUND(M66*O66*(1-P66),2)))),"") -> 523.69 | S66: -11.12 | T66: Second Class | U66: Digital Wallet
A67: ORD-1066 | B67: 45347 | C67: 2024-02-28 | D67: Ishaan Verma | E67: Consumer | F67: East | G67: =IF(TRIM(F67)="","",PROPER(TRIM(F67))) -> East | H67: California | I67: San Diego | J67: Furniture | K67: Tables | L67: Side Table | M67: 8 | N67: =IFERROR(IF(TRIM(M67)="","",IF(UPPER(TRIM(M67))="N/A","",IF(VALUE(M67)<0,"",VALUE(M67)))),"") -> 8 | O67: 319.71 | P67: 0.15 | Q67: 2174.03 | R67: =IFERROR(IF(Q67<>"",Q67,IF(OR(M67="",O67="",P67=""),"",IF(OR(M67<=0,O67<=0,P67<0,P67>1),"",ROUND(M67*O67*(1-P67),2)))),"") -> 2174.03 | S67: -5.23 | T67: First Class | U67: Card
A68: ORD-1067 | B68: 45029 | C68: 2023-04-16 | D68: Meera Patel | E68: Corporate | F68: Central | G68: =IF(TRIM(F68)="","",PROPER(TRIM(F68))) -> Central | H68: Illinois | I68: Springfield | J68: Office Supplies | K68: Paper | L68: Notebook Paper | M68: 1 | N68: =IFERROR(IF(TRIM(M68)="","",IF(UPPER(TRIM(M68))="N/A","",IF(VALUE(M68)<0,"",VALUE(M68)))),"") -> 1 | O68: 327.32 | P68: 0.15 | Q68: 278.22 | R68: =IFERROR(IF(Q68<>"",Q68,IF(OR(M68="",O68="",P68=""),"",IF(OR(M68<=0,O68<=0,P68<0,P68>1),"",ROUND(M68*O68*(1-P68),2)))),"") -> 278.22 | S68: 61.38 | T68: Same Day | U68: Card
A69: ORD-1068 | B69: 45617 | C69: 2024-11-22 | D69: Meera Patel | E69: Consumer | F69: Central | G69: =IF(TRIM(F69)="","",PROPER(TRIM(F69))) -> Central | H69: Illinois | I69: Springfield | J69: Office Supplies | K69: Binders | L69: Ring Binder | M69: 6 | N69: =IFERROR(IF(TRIM(M69)="","",IF(UPPER(TRIM(M69))="N/A","",IF(VALUE(M69)<0,"",VALUE(M69)))),"") -> 6 | O69: 285.05 | P69: 0.15 | Q69: 1453.76 | R69: =IFERROR(IF(Q69<>"",Q69,IF(OR(M69="",O69="",P69=""),"",IF(OR(M69<=0,O69<=0,P69<0,P69>1),"",ROUND(M69*O69*(1-P69),2)))),"") -> 1453.76 | S69: 321.71 | T69: Standard Class | U69: Digital Wallet
A70: ORD-1069 | B70: 45575 | C70: 2024-10-11 | D70: Dev Mehta | E70: Consumer | F70: Central | G70: =IF(TRIM(F70)="","",PROPER(TRIM(F70))) -> Central | H70: Washington | I70: Seattle | J70: Furniture | K70: Chairs | L70: Office Chair | M70: 8 | N70: =IFERROR(IF(TRIM(M70)="","",IF(UPPER(TRIM(M70))="N/A","",IF(VALUE(M70)<0,"",VALUE(M70)))),"") -> 8 | O70: 81.53 | P70: 0.1 | Q70: 587.02 | R70: =IFERROR(IF(Q70<>"",Q70,IF(OR(M70="",O70="",P70=""),"",IF(OR(M70<=0,O70<=0,P70<0,P70>1),"",ROUND(M70*O70*(1-P70),2)))),"") -> 587.02 | S70: 138.29 | T70: First Class | U70: Digital Wallet
A71: ORD-1070 | B71: 45177 | C71: 2023-09-15 | D71: Sara Khan | E71: Corporate | F71: East | G71: =IF(TRIM(F71)="","",PROPER(TRIM(F71))) -> East | H71: Illinois | I71: Springfield | J71: Furniture | K71: Tables | L71: Office Table | M71: 3 | N71: =IFERROR(IF(TRIM(M71)="","",IF(UPPER(TRIM(M71))="N/A","",IF(VALUE(M71)<0,"",VALUE(M71)))),"") -> 3 | O71: 83.13 | P71: 0 | Q71: 249.39 | R71: =IFERROR(IF(Q71<>"",Q71,IF(OR(M71="",O71="",P71=""),"",IF(OR(M71<=0,O71<=0,P71<0,P71>1),"",ROUND(M71*O71*(1-P71),2)))),"") -> 249.39 | S71: 25.03 | T71: Same Day | U71: Bank Transfer
A72: ORD-1071 | B72: 45188 | C72: 2023-09-21 | D72: Ishaan Verma | E72: Corporate | F72: Central | G72: =IF(TRIM(F72)="","",PROPER(TRIM(F72))) -> Central | H72: Washington | I72: Seattle | J72: Office Supplies | K72: Paper | L72: Copy Paper | M72: 8 | N72: =IFERROR(IF(TRIM(M72)="","",IF(UPPER(TRIM(M72))="N/A","",IF(VALUE(M72)<0,"",VALUE(M72)))),"") -> 8 | O72: 406.33 | P72: 0.3 | Q72: 2275.45 | R72: =IFERROR(IF(Q72<>"",Q72,IF(OR(M72="",O72="",P72=""),"",IF(OR(M72<=0,O72<=0,P72<0,P72>1),"",ROUND(M72*O72*(1-P72),2)))),"") -> 2275.45 | S72: 162.55 | T72: Same Day | U72: Bank Transfer
A73: ORD-1072 | B73: 45236 | C73: 2023-11-11 | D73: Riya Desai | E73: Consumer | F73: South | G73: =IF(TRIM(F73)="","",PROPER(TRIM(F73))) -> South | H73: New York | I73: Buffalo | J73: Office Supplies | K73: Paper | L73: Notebook Paper | M73: 8 | N73: =IFERROR(IF(TRIM(M73)="","",IF(UPPER(TRIM(M73))="N/A","",IF(VALUE(M73)<0,"",VALUE(M73)))),"") -> 8 | O73: 55.14 | P73: 0.15 | Q73: 374.95 | R73: =IFERROR(IF(Q73<>"",Q73,IF(OR(M73="",O73="",P73=""),"",IF(OR(M73<=0,O73<=0,P73<0,P73>1),"",ROUND(M73*O73*(1-P73),2)))),"") -> 374.95 | S73: 31.15 | T73: Standard Class | U73: Card
A74: ORD-1073 | B74: 45435 | C74: 2024-05-26 | D74: Meera Patel | E74: Home Office | F74: West | G74: =IF(TRIM(F74)="","",PROPER(TRIM(F74))) -> West | H74: Texas | I74: Houston | J74: Technology | K74: Phones | L74: Smartphone | M74: 6 | N74: =IFERROR(IF(TRIM(M74)="","",IF(UPPER(TRIM(M74))="N/A","",IF(VALUE(M74)<0,"",VALUE(M74)))),"") -> 6 | O74: 104.8 | P74: 0.05 | Q74: 597.36 | R74: =IFERROR(IF(Q74<>"",Q74,IF(OR(M74="",O74="",P74=""),"",IF(OR(M74<=0,O74<=0,P74<0,P74>1),"",ROUND(M74*O74*(1-P74),2)))),"") -> 597.36 | S74: 63.09 | T74: Same Day | U74: Card
A75: ORD-1074 | B75: 45300 | C75: 2024-01-12 | D75: Sara Khan | E75: Consumer | F75: Central | G75: =IF(TRIM(F75)="","",PROPER(TRIM(F75))) -> Central | H75: Washington | I75: Seattle | J75: Technology | K75: Phones | L75: Wireless Phone | M75: 2 | N75: =IFERROR(IF(TRIM(M75)="","",IF(UPPER(TRIM(M75))="N/A","",IF(VALUE(M75)<0,"",VALUE(M75)))),"") -> 2 | O75: 410.06 | P75: 0.1 | Q75: 738.11 | R75: =IFERROR(IF(Q75<>"",Q75,IF(OR(M75="",O75="",P75=""),"",IF(OR(M75<=0,O75<=0,P75<0,P75>1),"",ROUND(M75*O75*(1-P75),2)))),"") -> 738.11 | S75: 120.93 | T75: First Class | U75: Cash
A76: ORD-1075 | B76: 45420 | C76: 2024-05-11 | D76: Sara Khan | E76: Home Office | F76: South | G76: =IF(TRIM(F76)="","",PROPER(TRIM(F76))) -> South | H76: Texas | I76: Austin | J76: Office Supplies | K76: Binders | L76: File Binder | M76: 6 | N76: =IFERROR(IF(TRIM(M76)="","",IF(UPPER(TRIM(M76))="N/A","",IF(VALUE(M76)<0,"",VALUE(M76)))),"") -> 6 | O76: 363.47 | P76: 0.15 | Q76: 1853.7 | R76: =IFERROR(IF(Q76<>"",Q76,IF(OR(M76="",O76="",P76=""),"",IF(OR(M76<=0,O76<=0,P76<0,P76>1),"",ROUND(M76*O76*(1-P76),2)))),"") -> 1853.7 | S76: 487.4 | T76: First Class | U76: Card
A77: ORD-1076 | B77: 44941 | C77: 2023-01-20 | D77: Anaya Rao | E77: Home Office | F77: Central | G77: =IF(TRIM(F77)="","",PROPER(TRIM(F77))) -> Central | H77: Texas | I77: Austin | J77: Office Supplies | K77: Paper | L77: A4 Paper | M77: 2 | N77: =IFERROR(IF(TRIM(M77)="","",IF(UPPER(TRIM(M77))="N/A","",IF(VALUE(M77)<0,"",VALUE(M77)))),"") -> 2 | O77: 209.02 | P77: 0.1 | Q77: 292.63 | R77: =IFERROR(IF(Q77<>"",Q77,IF(OR(M77="",O77="",P77=""),"",IF(OR(M77<=0,O77<=0,P77<0,P77>1),"",ROUND(M77*O77*(1-P77),2)))),"") -> 292.63 | S77: 48.15 | T77: Second Class | U77: Digital Wallet
A78: ORD-1077 | B78: 45561 | C78: 2024-10-01 | D78: Anaya Rao | E78: Consumer | F78: East | G78: =IF(TRIM(F78)="","",PROPER(TRIM(F78))) -> East | H78: Illinois | I78: Springfield | J78: Furniture | K78: Chairs | L78: Ergo Chair | M78: 4 | N78: =IFERROR(IF(TRIM(M78)="","",IF(UPPER(TRIM(M78))="N/A","",IF(VALUE(M78)<0,"",VALUE(M78)))),"") -> 4 | O78: 294.26 | P78: 0.3 | Q78: 823.93 | R78: =IFERROR(IF(Q78<>"",Q78,IF(OR(M78="",O78="",P78=""),"",IF(OR(M78<=0,O78<=0,P78<0,P78>1),"",ROUND(M78*O78*(1-P78),2)))),"") -> 823.93 | S78: 163.94 | T78: Standard Class | U78: Bank Transfer
... A89: ORD-1088 | B89: 45608 | C89: 2024-11-14 | D89: Sara Khan | E89: Consumer | F89: South | G89: =IF(TRIM(F89)="","",PROPER(TRIM(F89))) -> South | H89: Florida | I89: Tampa | J89: Office Supplies | K89: Binders | L89: Ring Binder | M89: 1 | N89: =IFERROR(IF(TRIM(M89)="","",IF(UPPER(TRIM(M89))="N/A","",IF(VALUE(M89)<0,"",VALUE(M89)))),"") -> 1 | O89: 436.03 | P89: 0.2 | Q89: 348.82 | R89: =IFERROR(IF(Q89<>"",Q89,IF(OR(M89="",O89="",P89=""),"",IF(OR(M89<=0,O89<=0,P89<0,P89>1),"",ROUND(M89*O89*(1-P89),2)))),"") -> 348.82 | S89: -12.65 | T89: Standard Class | U89: Bank Transfer
A90: ORD-1089 | B90: 45303 | C90: 2024-01-21 | D90: Aarav Shah | E90: Home Office | F90: Central | G90: =IF(TRIM(F90)="","",PROPER(TRIM(F90))) -> Central | H90: California | I90: San Diego | J90: Technology | K90: Phones | M90: 4 | N90: =IFERROR(IF(TRIM(M90)="","",IF(UPPER(TRIM(M90))="N/A","",IF(VALUE(M90)<0,"",VALUE(M90)))),"") -> 4 | O90: 364.79 | P90: 0.2 | Q90: 1167.33 | R90: =IFERROR(IF(Q90<>"",Q90,IF(OR(M90="",O90="",P90=""),"",IF(OR(M90<=0,O90<=0,P90<0,P90>1),"",ROUND(M90*O90*(1-P90),2)))),"") -> 1167.33 | S90: 313.18 | T90: Second Class | U90: Bank Transfer
A91: ORD-1090 | B91: 45243 | C91: 2023-11-20 | D91: Meera Patel | E91: Consumer | F91: West | G91: =IF(TRIM(F91)="","",PROPER(TRIM(F91))) -> West | H91: Texas | I91: Dallas | J91: Technology | K91: Accessories | L91: Keyboard | M91: 1 | N91: =IFERROR(IF(TRIM(M91)="","",IF(UPPER(TRIM(M91))="N/A","",IF(VALUE(M91)<0,"",VALUE(M91)))),"") -> 1 | O91: 88.18 | P91: 0.05 | Q91: 83.77 | R91: =IFERROR(IF(Q91<>"",Q91,IF(OR(M91="",O91="",P91=""),"",IF(OR(M91<=0,O91<=0,P91<0,P91>1),"",ROUND(M91*O91*(1-P91),2)))),"") -> 83.77 | S91: 6.74 | T91: Second Class | U91: Digital Wallet
A92: ORD-1091 | B92: 45391 | C92: 2024-04-11 | D92: Aarav Shah | E92: Consumer | F92: East | G92: =IF(TRIM(F92)="","",PROPER(TRIM(F92))) -> East | H92: Texas | I92: Houston | J92: Office Supplies | K92: Paper | L92: Copy Paper | M92: 6 | N92: =IFERROR(IF(TRIM(M92)="","",IF(UPPER(TRIM(M92))="N/A","",IF(VALUE(M92)<0,"",VALUE(M92)))),"") -> 6 | O92: 145.74 | P92: 0.1 | Q92: 787 | R92: =IFERROR(IF(Q92<>"",Q92,IF(OR(M92="",O92="",P92=""),"",IF(OR(M92<=0,O92<=0,P92<0,P92>1),"",ROUND(M92*O92*(1-P92),2)))),"") -> 787 | S92: 139.57 | T92: Standard Class | U92: Card
A93: ORD-1092 | B93: 45380 | C93: 2024-04-07 | D93: Meera Patel | E93: Consumer | F93: South | G93: =IF(TRIM(F93)="","",PROPER(TRIM(F93))) -> South | H93: Washington | I93: Spokane | J93: Office Supplies | K93: Binders | L93: Ring Binder | M93: 8 | N93: =IFERROR(IF(TRIM(M93)="","",IF(UPPER(TRIM(M93))="N/A","",IF(VALUE(M93)<0,"",VALUE(M93)))),"") -> 8 | O93: 276.33 | P93: 0.15 | Q93: 1879.04 | R93: =IFERROR(IF(Q93<>"",Q93,IF(OR(M93="",O93="",P93=""),"",IF(OR(M93<=0,O93<=0,P93<0,P93>1),"",ROUND(M93*O93*(1-P93),2)))),"") -> 1879.04 | S93: -102.11 | T93: First Class | U93: Digital Wallet
A94: ORD-1093 | B94: 45610 | C94: 2024-11-18 | D94: Riya Desai | E94: Consumer | F94: East | G94: =IF(TRIM(F94)="","",PROPER(TRIM(F94))) -> East | H94: Texas | I94: Houston | J94: Technology | K94: Phones | L94: Smartphone | M94: 4 | N94: =IFERROR(IF(TRIM(M94)="","",IF(UPPER(TRIM(M94))="N/A","",IF(VALUE(M94)<0,"",VALUE(M94)))),"") -> 4 | O94: 182.71 | P94: 0.2 | Q94: 584.67 | R94: =IFERROR(IF(Q94<>"",Q94,IF(OR(M94="",O94="",P94=""),"",IF(OR(M94<=0,O94<=0,P94<0,P94>1),"",ROUND(M94*O94*(1-P94),2)))),"") -> 584.67 | S94: -90.51 | T94: First Class | U94: Bank Transfer
A95: ORD-1094 | B95: 44934 | C95: 2023-01-12 | D95: Dev Mehta | E95: Consumer | F95: South | G95: =IF(TRIM(F95)="","",PROPER(TRIM(F95))) -> South | H95: Florida | I95: Tampa | J95: Furniture | K95: Chairs | L95: Visitor Chair | M95: 7 | N95: =IFERROR(IF(TRIM(M95)="","",IF(UPPER(TRIM(M95))="N/A","",IF(VALUE(M95)<0,"",VALUE(M95)))),"") -> 7 | O95: 85.66 | P95: 0.15 | Q95: 509.68 | R95: =IFERROR(IF(Q95<>"",Q95,IF(OR(M95="",O95="",P95=""),"",IF(OR(M95<=0,O95<=0,P95<0,P95>1),"",ROUND(M95*O95*(1-P95),2)))),"") -> 509.68 | S95: 33.12 | T95: Standard Class | U95: Digital Wallet
A96: ORD-1095 | B96: 45397 | C96: 2024-04-20 | D96: Meera Patel | E96: Corporate | F96: West | G96: =IF(TRIM(F96)="","",PROPER(TRIM(F96))) -> West | H96: California | I96: San Diego | J96: Furniture | K96: Chairs | L96: Office Chair | M96: 7 | N96: =IFERROR(IF(TRIM(M96)="","",IF(UPPER(TRIM(M96))="N/A","",IF(VALUE(M96)<0,"",VALUE(M96)))),"") -> 7 | O96: 261.44 | P96: 0.3 | Q96: 1281.06 | R96: =IFERROR(IF(Q96<>"",Q96,IF(OR(M96="",O96="",P96=""),"",IF(OR(M96<=0,O96<=0,P96<0,P96>1),"",ROUND(M96*O96*(1-P96),2)))),"") -> 1281.06 | S96: 146.64 | T96: Second Class | U96: Digital Wallet
A97: ORD-1096 | B97: 45297 | C97: 2024-01-08 | D97: Anaya Rao | E97: Corporate | F97: Central | G97: =IF(TRIM(F97)="","",PROPER(TRIM(F97))) -> Central | H97: California | I97: San Diego | J97: Technology | K97: Accessories | L97: Keyboard | M97: 2 | N97: =IFERROR(IF(TRIM(M97)="","",IF(UPPER(TRIM(M97))="N/A","",IF(VALUE(M97)<0,"",VALUE(M97)))),"") -> 2 | O97: 115.55 | P97: 0.2 | Q97: 184.88 | R97: =IFERROR(IF(Q97<>"",Q97,IF(OR(M97="",O97="",P97=""),"",IF(OR(M97<=0,O97<=0,P97<0,P97>1),"",ROUND(M97*O97*(1-P97),2)))),"") -> 184.88 | S97: 0.78 | T97: First Class | U97: Cash
A98: ORD-1097 | B98: 45449 | C98: 2024-06-09 | D98: Sara Khan | E98: Consumer | F98: East | G98: =IF(TRIM(F98)="","",PROPER(TRIM(F98))) -> East | H98: Washington | I98: Seattle | J98: Furniture | K98: Chairs | L98: Office Chair | M98: 4 | N98: =IFERROR(IF(TRIM(M98)="","",IF(UPPER(TRIM(M98))="N/A","",IF(VALUE(M98)<0,"",VALUE(M98)))),"") -> 4 | O98: 408.42 | P98: 0.1 | Q98: 1470.31 | R98: =IFERROR(IF(Q98<>"",Q98,IF(OR(M98="",O98="",P98=""),"",IF(OR(M98<=0,O98<=0,P98<0,P98>1),"",ROUND(M98*O98*(1-P98),2)))),"") -> 1470.31 | S98: -27.19 | T98: Second Class | U98: Cash
A99: ORD-1098 | B99: 45083 | C99: 2023-06-14 | D99: Dev Mehta | E99: Home Office | F99: Central | G99: =IF(TRIM(F99)="","",PROPER(TRIM(F99))) -> Central | H99: Washington | I99: Seattle | J99: Technology | K99: Phones | L99: Desk Phone | M99: 3 | N99: =IFERROR(IF(TRIM(M99)="","",IF(UPPER(TRIM(M99))="N/A","",IF(VALUE(M99)<0,"",VALUE(M99)))),"") -> 3 | O99: 428.47 | P99: 0.3 | Q99: 899.79 | R99: =IFERROR(IF(Q99<>"",Q99,IF(OR(M99="",O99="",P99=""),"",IF(OR(M99<=0,O99<=0,P99<0,P99>1),"",ROUND(M99*O99*(1-P99),2)))),"") -> 899.79 | S99: 42.55 | T99: Same Day | U99: Card
A100: ORD-1099 | B100: 45379 | C100: 2024-04-02 | D100: Ishaan Verma | E100: Corporate | F100: West | G100: =IF(TRIM(F100)="","",PROPER(TRIM(F100))) -> West | H100: Washington | I100: Spokane | J100: Office Supplies | K100: Paper | L100: A4 Paper | M100: 5 | N100: =IFERROR(IF(TRIM(M100)="","",IF(UPPER(TRIM(M100))="N/A","",IF(VALUE(M100)<0,"",VALUE(M100)))),"") -> 5 | O100: 269.41 | P100: 0.1 | Q100: 1212.35 | R100: =IFERROR(IF(Q100<>"",Q100,IF(OR(M100="",O100="",P100=""),"",IF(OR(M100<=0,O100<=0,P100<0,P100>1),"",ROUND(M100*O100*(1-P100),2)))),"") -> 1212.35 | S100: 64.71 | T100: First Class | U100: Bank Transfer
A101: ORD-1100 | B101: 45587 | C101: 2024-10-23 | D101: Ishaan Verma | E101: Home Office | F101: East | G101: =IF(TRIM(F101)="","",PROPER(TRIM(F101))) -> East | H101: California | I101: San Francisco | J101: Furniture | K101: Chairs | L101: Office Chair | M101: 7 | N101: =IFERROR(IF(TRIM(M101)="","",IF(UPPER(TRIM(M101))="N/A","",IF(VALUE(M101)<0,"",VALUE(M101)))),"") -> 7 | O101: 212.52 | P101: 0.2 | Q101: 1190.11 | R101: =IFERROR(IF(Q101<>"",Q101,IF(OR(M101="",O101="",P101=""),"",IF(OR(M101<=0,O101<=0,P101<0,P101>1),"",ROUND(M101*O101*(1-P101),2)))),"") -> 1190.11 | S101: 308.17 | T101: Same Day | U101: Cash
A102: ORD-1101 | B102: 45388 | C102: 2024-04-14 | D102: Ishaan Verma | E102: Home Office | F102: East | G102: =IF(TRIM(F102)="","",PROPER(TRIM(F102))) -> East | H102: California | I102: San Diego | J102: Furniture | K102: Chairs | L102: Office Chair | M102: 2 | N102: =IFERROR(IF(TRIM(M102)="","",IF(UPPER(TRIM(M102))="N/A","",IF(VALUE(M102)<0,"",VALUE(M102)))),"") -> 2 | O102: 231.01 | P102: 0.05 | Q102: 438.92 | R102: =IFERROR(IF(Q102<>"",Q102,IF(OR(M102="",O102="",P102=""),"",IF(OR(M102<=0,O102<=0,P102<0,P102>1),"",ROUND(M102*O102*(1-P102),2)))),"") -> 438.92 | S102: -71.1 | T102: First Class | U102: Bank Transfer
... A105: ORD-1104 | B105: 45613 | C105: 2024-11-18 | D105: Dev Mehta | E105: Corporate | F105: East | G105: =IF(TRIM(F105)="","",PROPER(TRIM(F105))) -> East | H105: Washington | I105: Tacoma | J105: Furniture | K105: Tables | L105: Office Table | M105: 2 | N105: =IFERROR(IF(TRIM(M105)="","",IF(UPPER(TRIM(M105))="N/A","",IF(VALUE(M105)<0,"",VALUE(M105)))),"") -> 2 | O105: 293.54 | P105: 0.15 | Q105: 499.02 | R105: =IFERROR(IF(Q105<>"",Q105,IF(OR(M105="",O105="",P105=""),"",IF(OR(M105<=0,O105<=0,P105<0,P105>1),"",ROUND(M105*O105*(1-P105),2)))),"") -> 499.02 | S105: 26.9 | T105: First Class | U105: Digital Wallet
A106: ORD-1105 | C106: 2023-08-29 | D106: Aarav Shah | E106: Home Office | F106: Central | G106: =IF(TRIM(F106)="","",PROPER(TRIM(F106))) -> Central | H106: New York | I106: New York City | J106: Furniture | K106: Tables | L106: Side Table | M106: 2 | N106: =IFERROR(IF(TRIM(M106)="","",IF(UPPER(TRIM(M106))="N/A","",IF(VALUE(M106)<0,"",VALUE(M106)))),"") -> 2 | O106: 138.74 | P106: 0 | Q106: 277.48 | R106: =IFERROR(IF(Q106<>"",Q106,IF(OR(M106="",O106="",P106=""),"",IF(OR(M106<=0,O106<=0,P106<0,P106>1),"",ROUND(M106*O106*(1-P106),2)))),"") -> 277.48 | S106: 14.86 | T106: Second Class | U106: Digital Wallet
A107: ORD-1106 | B107: 45093 | C107: 2023-06-20 | D107: Ishaan Verma | E107: Home Office | F107: Central | G107: =IF(TRIM(F107)="","",PROPER(TRIM(F107))) -> Central | H107: New York | I107: Albany | J107: Furniture | K107: Tables | L107: Side Table | M107: 3 | N107: =IFERROR(IF(TRIM(M107)="","",IF(UPPER(TRIM(M107))="N/A","",IF(VALUE(M107)<0,"",VALUE(M107)))),"") -> 3 | O107: 326.76 | P107: 0 | Q107: 980.28 | R107: =IFERROR(IF(Q107<>"",Q107,IF(OR(M107="",O107="",P107=""),"",IF(OR(M107<=0,O107<=0,P107<0,P107>1),"",ROUND(M107*O107*(1-P107),2)))),"") -> 980.28 | S107: 8.82 | T107: Same Day | U107: Cash
A108: ORD-1107 | B108: 45171 | C108: 2023-09-10 | D108: Riya Desai | E108: Corporate | F108: South | G108: =IF(TRIM(F108)="","",PROPER(TRIM(F108))) -> South | H108: Texas | I108: Dallas | J108: Technology | K108: Phones | L108: Desk Phone | M108: 4 | N108: =IFERROR(IF(TRIM(M108)="","",IF(UPPER(TRIM(M108))="N/A","",IF(VALUE(M108)<0,"",VALUE(M108)))),"") -> 4 | O108: 170.59 | P108: 0.2 | Q108: 545.89 | R108: =IFERROR(IF(Q108<>"",Q108,IF(OR(M108="",O108="",P108=""),"",IF(OR(M108<=0,O108<=0,P108<0,P108>1),"",ROUND(M108*O108*(1-P108),2)))),"") -> 545.89 | S108: 148.94 | T108: Second Class | U108: Cash
A109: ORD-1108 | B109: 44980 | C109: 2023-03-04 | D109: Meera Patel | E109: Corporate | F109: West | G109: =IF(TRIM(F109)="","",PROPER(TRIM(F109))) -> West | H109: Washington | I109: Spokane | J109: Office Supplies | K109: Binders | L109: Ring Binder | M109: 6 | N109: =IFERROR(IF(TRIM(M109)="","",IF(UPPER(TRIM(M109))="N/A","",IF(VALUE(M109)<0,"",VALUE(M109)))),"") -> 6 | O109: 253.11 | P109: 0 | Q109: 1518.66 | R109: =IFERROR(IF(Q109<>"",Q109,IF(OR(M109="",O109="",P109=""),"",IF(OR(M109<=0,O109<=0,P109<0,P109>1),"",ROUND(M109*O109*(1-P109),2)))),"") -> 1518.66 | S109: 223.61 | T109: First Class | U109: Digital Wallet
A110: ORD-1109 | B110: 45077 | C110: 2023-06-07 | D110: Aarav Shah | E110: Corporate | F110: Central | G110: =IF(TRIM(F110)="","",PROPER(TRIM(F110))) -> Central | H110: Florida | I110: Miami | J110: Technology | K110: Phones | L110: Desk Phone | M110: 4 | N110: =IFERROR(IF(TRIM(M110)="","",IF(UPPER(TRIM(M110))="N/A","",IF(VALUE(M110)<0,"",VALUE(M110)))),"") -> 4 | O110: 368.98 | P110: 0.1 | Q110: 1328.33 | R110: =IFERROR(IF(Q110<>"",Q110,IF(OR(M110="",O110="",P110=""),"",IF(OR(M110<=0,O110<=0,P110<0,P110>1),"",ROUND(M110*O110*(1-P110),2)))),"") -> 1328.33 | S110: 329.45 | T110: Same Day | U110: Card
A111: ORD-1110 | B111: 45156 | C111: 2023-08-21 | D111: Kabir Joshi | E111: Consumer | F111: Central | G111: =IF(TRIM(F111)="","",PROPER(TRIM(F111))) -> Central | H111: California | I111: San Diego | J111: Office Supplies | K111: Binders | L111: Presentation Binder | M111: 2 | N111: =IFERROR(IF(TRIM(M111)="","",IF(UPPER(TRIM(M111))="N/A","",IF(VALUE(M111)<0,"",VALUE(M111)))),"") -> 2 | O111: 378.92 | P111: 0.3 | Q111: 530.49 | R111: =IFERROR(IF(Q111<>"",Q111,IF(OR(M111="",O111="",P111=""),"",IF(OR(M111<=0,O111<=0,P111<0,P111>1),"",ROUND(M111*O111*(1-P111),2)))),"") -> 530.49 | S111: -13.67 | T111: Second Class | U111: Digital Wallet
A112: ORD-1111 | B112: 45557 | C112: 2024-10-01 | D112: Anaya Rao | E112: Consumer | F112: Central | G112: =IF(TRIM(F112)="","",PROPER(TRIM(F112))) -> Central | H112: California | I112: Los Angeles | J112: Office Supplies | K112: Paper | L112: A4 Paper | M112: 1 | N112: =IFERROR(IF(TRIM(M112)="","",IF(UPPER(TRIM(M112))="N/A","",IF(VALUE(M112)<0,"",VALUE(M112)))),"") -> 1 | O112: 121.12 | P112: 0.05 | Q112: 115.06 | R112: =IFERROR(IF(Q112<>"",Q112,IF(OR(M112="",O112="",P112=""),"",IF(OR(M112<=0,O112<=0,P112<0,P112>1),"",ROUND(M112*O112*(1-P112),2)))),"") -> 115.06 | S112: 8.34 | T112: First Class | U112: Card
A113: ORD-1112 | B113: 45171 | C113: 2023-09-03 | D113: Sara Khan | E113: Home Office | F113: East | G113: =IF(TRIM(F113)="","",PROPER(TRIM(F113))) -> East | H113: Florida | I113: Tampa | J113: Furniture | K113: Chairs | L113: Office Chair | M113: 8 | N113: =IFERROR(IF(TRIM(M113)="","",IF(UPPER(TRIM(M113))="N/A","",IF(VALUE(M113)<0,"",VALUE(M113)))),"") -> 8 | O113: 35.76 | P113: 0.15 | Q113: 243.17 | R113: =IFERROR(IF(Q113<>"",Q113,IF(OR(M113="",O113="",P113=""),"",IF(OR(M113<=0,O113<=0,P113<0,P113>1),"",ROUND(M113*O113*(1-P113),2)))),"") -> 243.17 | S113: 22.98 | T113: Same Day | U113: Card
A114: ORD-1113 | B114: 45288 | C114: 2024-01-03 | D114: Meera Patel | E114: Home Office | F114: West | G114: =IF(TRIM(F114)="","",PROPER(TRIM(F114))) -> West | H114: New York | I114: Albany | J114: Technology | K114: Phones | L114: Smartphone | M114: 7 | N114: =IFERROR(IF(TRIM(M114)="","",IF(UPPER(TRIM(M114))="N/A","",IF(VALUE(M114)<0,"",VALUE(M114)))),"") -> 7 | O114: 90.79 | P114: 0.3 | Q114: 444.87 | R114: =IFERROR(IF(Q114<>"",Q114,IF(OR(M114="",O114="",P114=""),"",IF(OR(M114<=0,O114<=0,P114<0,P114>1),"",ROUND(M114*O114*(1-P114),2)))),"") -> 444.87 | S114: -62.56 | T114: Same Day | U114: Card
A115: ORD-1114 | B115: 45323 | C115: 2024-02-03 | D115: Dev Mehta | E115: Consumer | F115: West | G115: =IF(TRIM(F115)="","",PROPER(TRIM(F115))) -> West | H115: Texas | I115: Dallas | J115: Technology | K115: Accessories | L115: Mouse | M115: 1 | N115: =IFERROR(IF(TRIM(M115)="","",IF(UPPER(TRIM(M115))="N/A","",IF(VALUE(M115)<0,"",VALUE(M115)))),"") -> 1 | O115: 165.84 | P115: 0 | Q115: 165.84 | R115: =IFERROR(IF(Q115<>"",Q115,IF(OR(M115="",O115="",P115=""),"",IF(OR(M115<=0,O115<=0,P115<0,P115>1),"",ROUND(M115*O115*(1-P115),2)))),"") -> 165.84 | S115: -3.55 | T115: First Class | U115: Cash
A116: ORD-1115 | B116: 45402 | C116: 2024-04-28 | D116: Aarav Shah | E116: Corporate | F116: East | G116: =IF(TRIM(F116)="","",PROPER(TRIM(F116))) -> East | H116: Washington | I116: Spokane | J116: Technology | K116: Accessories | L116: Keyboard | M116: 3 | N116: =IFERROR(IF(TRIM(M116)="","",IF(UPPER(TRIM(M116))="N/A","",IF(VALUE(M116)<0,"",VALUE(M116)))),"") -> 3 | O116: 366.68 | P116: 0 | Q116: 1100.04 | R116: =IFERROR(IF(Q116<>"",Q116,IF(OR(M116="",O116="",P116=""),"",IF(OR(M116<=0,O116<=0,P116<0,P116>1),"",ROUND(M116*O116*(1-P116),2)))),"") -> 1100.04 | S116: 164.32 | T116: Second Class | U116: Card
A117: ORD-1116 | B117: 45244 | C117: 2023-11-20 | D117: Aarav Shah | E117: Home Office | F117: Central | G117: =IF(TRIM(F117)="","",PROPER(TRIM(F117))) -> Central | H117: Illinois | I117: Springfield | J117: Office Supplies | K117: Binders | L117: Presentation Binder | M117: 8 | N117: =IFERROR(IF(TRIM(M117)="","",IF(UPPER(TRIM(M117))="N/A","",IF(VALUE(M117)<0,"",VALUE(M117)))),"") -> 8 | O117: 119.96 | P117: 0.3 | Q117: 671.78 | R117: =IFERROR(IF(Q117<>"",Q117,IF(OR(M117="",O117="",P117=""),"",IF(OR(M117<=0,O117<=0,P117<0,P117>1),"",ROUND(M117*O117*(1-P117),2)))),"") -> 671.78 | S117: -61.87 | T117: Standard Class | U117: Bank Transfer
A118: ORD-1117 | B118: 45336 | C118: 2024-02-22 | D118: Dev Mehta | E118: Home Office | F118: Central | G118: =IF(TRIM(F118)="","",PROPER(TRIM(F118))) -> Central | H118: Washington | I118: Spokane | J118: Office Supplies | K118: Paper | L118: A4 Paper | M118: 7 | N118: =IFERROR(IF(TRIM(M118)="","",IF(UPPER(TRIM(M118))="N/A","",IF(VALUE(M118)<0,"",VALUE(M118)))),"") -> 7 | O118: 157.85 | P118: 0.05 | Q118: 1049.7 | R118: =IFERROR(IF(Q118<>"",Q118,IF(OR(M118="",O118="",P118=""),"",IF(OR(M118<=0,O118<=0,P118<0,P118>1),"",ROUND(M118*O118*(1-P118),2)))),"") -> 1049.7 | S118: 50.65 | T118: Same Day | U118: Card
... A120: ORD-1119 | B120: 44970 | C120: 2023-02-20 | D120: Dev Mehta | E120: Home Office | F120: East | G120: =IF(TRIM(F120)="","",PROPER(TRIM(F120))) -> East | H120: Washington | I120: Spokane | J120: Office Supplies | K120: Paper | L120: A4 Paper | M120: 7 | N120: =IFERROR(IF(TRIM(M120)="","",IF(UPPER(TRIM(M120))="N/A","",IF(VALUE(M120)<0,"",VALUE(M120)))),"") -> 7 | O120: 129.35 | P120: 0 | Q120: 905.45 | R120: =IFERROR(IF(Q120<>"",Q120,IF(OR(M120="",O120="",P120=""),"",IF(OR(M120<=0,O120<=0,P120<0,P120>1),"",ROUND(M120*O120*(1-P120),2)))),"") -> 905.45 | S120: -131.73 | T120: Second Class | U120: Digital Wallet
A121: ORD-1120 | B121: 45056 | C121: 2023-05-13 | D121: Ishaan Verma | E121: Corporate | F121: Central | G121: =IF(TRIM(F121)="","",PROPER(TRIM(F121))) -> Central | H121: California | I121: Los Angeles | J121: Furniture | K121: Chairs | L121: Office Chair | M121: 6 | N121: =IFERROR(IF(TRIM(M121)="","",IF(UPPER(TRIM(M121))="N/A","",IF(VALUE(M121)<0,"",VALUE(M121)))),"") -> 6 | O121: 168.07 | Q121: 806.74 | R121: =IFERROR(IF(Q121<>"",Q121,IF(OR(M121="",O121="",P121=""),"",IF(OR(M121<=0,O121<=0,P121<0,P121>1),"",ROUND(M121*O121*(1-P121),2)))),"") -> 806.74 | S121: -133.19 | T121: Standard Class | U121: Cash
A122: ORD-1121 | B122: 45302 | C122: 2024-01-14 | D122: Ishaan Verma | E122: Home Office | F122: South | G122: =IF(TRIM(F122)="","",PROPER(TRIM(F122))) -> South | H122: Florida | I122: Orlando | J122: Technology | K122: Phones | L122: Wireless Phone | M122: 5 | N122: =IFERROR(IF(TRIM(M122)="","",IF(UPPER(TRIM(M122))="N/A","",IF(VALUE(M122)<0,"",VALUE(M122)))),"") -> 5 | O122: 118.33 | P122: 0 | Q122: 591.65 | R122: =IFERROR(IF(Q122<>"",Q122,IF(OR(M122="",O122="",P122=""),"",IF(OR(M122<=0,O122<=0,P122<0,P122>1),"",ROUND(M122*O122*(1-P122),2)))),"") -> 591.65 | S122: -99.44 | T122: Standard Class | U122: Bank Transfer
...

Sheet KPI
A1: Sales_Analysis
A3: KPI
A4: Total Sales | B4: =SUM(Dirty_Retail_Data!O2:O251) -> 213895.44
A5: Total Cleaned Sales | B5: =SUM(Retailed_Data!R2:R251) -> 214419.13
A6: Total Profit | B6: =SUM(Retailed_Data!S2:S251) -> 8261.65
A7: Profit Margin | B7: =IFERROR(B6/B5,0) -> 0.038530377
A8: Total Orders | B8: =COUNTA(Retailed_Data!A2:A251) -> 250
A9: Total Units Sold | B9: =SUM(Retailed_Data!M2:M251) -> 1148
A10: Total Cleaned Units Sold | B10: =SUM(Retailed_Data!N2:N251) -> 1151

Sheet Category_Analysis
A3: Row Labels | B3: Sum of Sales_cleaned | C3: Sum of Profit | D3: Profit Margin
A4: Furniture | B4: 56783.44 | C4: 2049.11 | D4: =IFERROR(C4/B4,0) -> 0.036086401
A5: Office Supplies | B5: 94587.46 | C5: 3935.36 | D5: =IFERROR(C5/B5,0) -> 0.041605515
A6: Technology | B6: 63048.23 | C6: 2277.18 | D6: =IFERROR(C6/B6,0) -> 0.036118064
A7: Grand Total | B7: 214419.13 | C7: 8261.65

Sheet Region_Analysis
A3: Row Labels | B3: Sum of Sales_cleaned | C3: Sum of Profit | D3: Profit_Margin
A4: Central | B4: 55778.1 | C4: 2624.5 | D4: =+IFERROR(C4/B4,0) -> 0.047052517
A5: East | B5: 57446.1 | C5: 1528.39 | D5: =+IFERROR(C5/B5,0) -> 0.026605636
A6: South | B6: 47670.7 | C6: 2448.85 | D6: =+IFERROR(C6/B6,0) -> 0.051370129
A7: West | B7: 53216.12 | C7: 1685.52 | D7: =+IFERROR(C7/B7,0) -> 0.03167311
A8: Unknown | B8: 308.11 | C8: -25.61 | D8: =+IFERROR(C8/B8,0) -> -0.083119665
A9: Grand Total | B9: 214419.13 | C9: 8261.65

Sheet Sales & Profit by Sub-Category
A3: Row Labels | B3: Sum of Sales_cleaned | C3: Sum of Profit
A4: Accessories | B4: 33351.86 | C4: 563.54
A5: Binders | B5: 48786.35 | C5: 2579
A6: Chairs | B6: 32358.68 | C6: 1807.22
A7: Paper | B7: 45801.11 | C7: 1356.36
A8: Phones | B8: 29696.37 | C8: 1713.64
A9: Tables | B9: 24424.76 | C9: 241.89
A10: Grand Total | B10: 214419.13 | C10: 8261.65

Sheet Discount_Analysis
A3: Row Labels | B3: Sum of Sales_cleaned | C3: Sum of Profit
A4: 0 | B4: 43273.45 | C4: 2012.99
A5: 0.05 | B5: 41684.7 | C5: 2017.76
A6: 0.1 | B6: 31252.51 | C6: 1652.98
A7: 0.15 | B7: 42533.4 | C7: 663.16
A8: 0.2 | B8: 29542.22 | C8: 635.2
A9: 0.3 | B9: 24419.72 | C9: 1471.8
A10: (blank) | B10: 1713.13 | C10: -192.24
A11: Grand Total | B11: 214419.13 | C11: 8261.65
